{
  "department": "204",
  "calendar_kind": null,
  "scraped_at": "2026-05-04T01:40:45.107Z",
  "source_url": "https://webapps.sftc.org/tr/tr.dll?RulingID=7&SessionID=ECCAE0248B8AA8168BFE049183FF8E7667A2A4EB",
  "reported_total": 69,
  "rulings": [
    {
      "Case Number": "PES99272715",
      "Case Title": "ESTATE OF ALFRED ONG WONG",
      "Court Date": "2014-09-23 09:00 AM",
      "Examiner": "HELEN TROWBRIDGE",
      "Calendar Matter": "REPORT OF SALE AND PETITION TO CONFIRM SALE OF REAL PROPERTY (1510-1512 Pacific Ave. S.F.)",
      "Rulings": "Hearing",
      "Judge": "Helen Trowbridge"
    },
    {
      "Case Number": "PTR00280084",
      "Case Title": "IN THE MATTER OF THE FLORENCE BALDOCCHI 1997 TRUST DATED OCTOBER 17,1997",
      "Court Date": "2014-09-23 09:00 AM",
      "Examiner": "SEAN BANG",
      "Calendar Matter": "FUTURE ACCOUNTING",
      "Rulings": "off calendar",
      "Judge": "Sean Bang"
    },
    {
      "Case Number": "PCN05287403",
      "Case Title": "CONSERVATORSHIP OF ALBERTA MOORE-LEUBE",
      "Court Date": "2014-09-23 09:00 AM",
      "Examiner": "PAMELA MEYERS",
      "Calendar Matter": "FUTURE ACCOUNTING",
      "Rulings": "status is off calendar",
      "Judge": "Pamela Meyers"
    },
    {
      "Case Number": "PCN06288735",
      "Case Title": "CONSERVATORSHIP OF RALPH G. VOSSEN",
      "Court Date": "2014-09-23 09:00 AM",
      "Examiner": "TRUDY J. VERZOSA",
      "Calendar Matter": "ACCOUNTING PETITION RE: ACCOUNTING #3, REPORT, FEES",
      "Rulings": "Conitnued to 10/7/14 at request of counsel",
      "Judge": "Trudy J. Verzosa"
    },
    {
      "Case Number": "PES06289117",
      "Case Title": "THE ESTATE OF JOHN PETERSEN",
      "Court Date": "2014-09-23 09:00 AM",
      "Examiner": "TRUDY J. VERZOSA",
      "Calendar Matter": "ACCOUNTING PETITION RE: ACCOUNTING #1, REPORT, FEES",
      "Rulings": "Grant without hearing",
      "Judge": "Trudy J. Verzosa"
    },
    {
      "Case Number": "PCN06289365",
      "Case Title": "CONSERVATORSHIP OF GWENDOLYN NELICE MCGRAW",
      "Court Date": "2014-09-23 09:00 AM",
      "Examiner": "SANDRA HILTON",
      "Calendar Matter": "FUTURE ACCOUNTING",
      "Rulings": "off calendar",
      "Judge": "Sandra Hilton"
    },
    {
      "Case Number": "PES08291831",
      "Case Title": "THE ESTATE OF CHRISTINE YOUNG",
      "Court Date": "2014-09-23 09:00 AM",
      "Examiner": "PAMELA MEYERS",
      "Calendar Matter": "Petition For Suspension Of Powers And Removal Of Representative And For Order Declaring Deed Null And Void",
      "Rulings": "appearance is required",
      "Judge": "Pamela Meyers"
    },
    {
      "Case Number": "PES08291831",
      "Case Title": "THE ESTATE OF CHRISTINE YOUNG",
      "Court Date": "2014-09-23 09:00 AM",
      "Examiner": "PAMELA MEYERS",
      "Calendar Matter": "Petition For Statutory And Extraordinary Fees By Former Counsel To Administrator",
      "Rulings": "appearance required",
      "Judge": "Pamela Meyers"
    },
    {
      "Case Number": "PES08291915",
      "Case Title": "THE ESTATE OF DAVID B. BOYCE",
      "Court Date": "2014-09-23 09:00 AM",
      "Examiner": "SANDRA HILTON",
      "Calendar Matter": "ACCOUNTING PETITION RE: ACCOUNTING #1, REPORT, FEES, FINAL DISTRIBUTION",
      "Rulings": "Grant without appearance. Order modified by the court re the payment of the late filed creditor's claim.",
      "Judge": "Sandra Hilton"
    },
    {
      "Case Number": "PCN08291975",
      "Case Title": "CONSERVATORSHIP OF HILDEGARD OPFERMANN",
      "Court Date": "2014-09-23 09:00 AM",
      "Examiner": "PAMELA MEYERS",
      "Calendar Matter": "ACCOUNTING PETITION RE: ACCOUNTING #4, REPORT, FEES",
      "Rulings": "petition approved; no appearance is required",
      "Judge": "Pamela Meyers"
    },
    {
      "Case Number": "PTR09292798",
      "Case Title": "IN RE THE WANETA A AVERHOFF TRUST, DATED MAY 24, 1996",
      "Court Date": "2014-09-23 09:00 AM",
      "Examiner": "HELEN TROWBRIDGE",
      "Calendar Matter": "ACCOUNTING PETITION RE: ACCOUNTING #4, REPORT, FEES, FINAL DISTRIBUTION",
      "Rulings": "Grant without hearing",
      "Judge": "Helen Trowbridge"
    },
    {
      "Case Number": "PES10293236",
      "Case Title": "THE ESTATE OF RONALD C. BERTOLOZZI",
      "Court Date": "2014-09-23 09:00 AM",
      "Examiner": "SANDRA HILTON",
      "Calendar Matter": "ACCOUNTING PETITION RE: ACCOUNTING #1, REPORT, FEES, FINAL DISTRIBUTION",
      "Rulings": "Hearing. Appearance required.",
      "Judge": "Sandra Hilton"
    },
    {
      "Case Number": "PES10293835",
      "Case Title": "THE ESTATE OF EDWARD JOHN MCELLIGOTT",
      "Court Date": "2014-09-23 09:00 AM",
      "Examiner": "SANDRA HILTON",
      "Calendar Matter": "ADDED TO CALENDAR FOR Status On Filing Of Inventory And Appraisal; Petition For Final Distribution Or Report On Status Of Administration",
      "Rulings": "Hearing. Appearance required for the personal representative to update the court on progress in getting this estate closed. No hearing notes will be sent.",
      "Judge": "Sandra Hilton"
    },
    {
      "Case Number": "PCN10293938",
      "Case Title": "CONSERVATORSHIP OF VIRGINIA ROSE",
      "Court Date": "2014-09-23 09:00 AM",
      "Examiner": "HELEN TROWBRIDGE",
      "Calendar Matter": "ACCOUNTING PETITION RE: ACCOUNTING #2, REPORT, FEES",
      "Rulings": "Continued to 10/21/14. No response to Examiner's Notes.",
      "Judge": "Helen Trowbridge"
    },
    {
      "Case Number": "PCN10294032",
      "Case Title": "CONSERVATORSHIP OF J.B. JACKSON",
      "Court Date": "2014-09-23 09:00 AM",
      "Examiner": "SANDRA HILTON",
      "Calendar Matter": "ACCOUNTING PETITION RE: ACCOUNTING #2, REPORT, FEES",
      "Rulings": "Grant without hearing.",
      "Judge": "Sandra Hilton"
    },
    {
      "Case Number": "PTR10294040",
      "Case Title": "IN THE MATTER OF THE J.B. JACKSON AND MINNIE O. JACKSON REVOCABLE TRUST",
      "Court Date": "2014-09-23 09:00 AM",
      "Examiner": "SANDRA HILTON",
      "Calendar Matter": "ACCOUNTING PETITION RE: ACCOUNTING #2, REPORT, FEES",
      "Rulings": "Grant without hearing.",
      "Judge": "Sandra Hilton"
    },
    {
      "Case Number": "PTR11294924",
      "Case Title": "IN THE MATTER OF THE JOHN A. SCANNELL et al TRUST",
      "Court Date": "2014-09-23 09:00 AM",
      "Examiner": "HELEN TROWBRIDGE",
      "Calendar Matter": "ACCOUNTING PETITION RE: ACCOUNTING #4",
      "Rulings": "Continued to 10/21/14. No response to Examiner's Notes. No courtesy copies.",
      "Judge": "Helen Trowbridge"
    },
    {
      "Case Number": "PCN11294956",
      "Case Title": "CONSERVATORSHIP OF LUCIA FIORANI",
      "Court Date": "2014-09-23 09:00 AM",
      "Examiner": "SANDRA HILTON",
      "Calendar Matter": "Petition For Approval Of Third Status Report Of Cons. Of The Estate Of Conservatee",
      "Rulings": "Grant without hearing.",
      "Judge": "Sandra Hilton"
    },
    {
      "Case Number": "PES11295146",
      "Case Title": "THE ESTATE OF CARLA CATHERINA FERRANDO",
      "Court Date": "2014-09-23 09:00 AM",
      "Examiner": "TRUDY J. VERZOSA",
      "Calendar Matter": "ACCOUNTING PETITION RE: REPORT, FEES, FINAL DISTRIBUTION",
      "Rulings": "Grant without hearing",
      "Judge": "Trudy J. Verzosa"
    },
    {
      "Case Number": "PES11295276",
      "Case Title": "THE ESTATE OF STANFORD A. THOMSON",
      "Court Date": "2014-09-23 10:30 AM",
      "Examiner": "PAMELA MEYERS",
      "Calendar Matter": "PETITION FOR INSTRUCTIONS",
      "Rulings": "petition approved",
      "Judge": "Pamela Meyers"
    },
    {
      "Case Number": "PCN12295465",
      "Case Title": "CONSERVATORSHIP OF EMMA ANN FRIED",
      "Court Date": "2014-09-23 09:00 AM",
      "Examiner": "HELEN TROWBRIDGE",
      "Calendar Matter": "ACCOUNTING PETITION RE: ACCOUNTING #2, REPORT, FEES",
      "Rulings": "Continued to 10/21/14. Notes sent.",
      "Judge": "Helen Trowbridge"
    },
    {
      "Case Number": "PCN12296284",
      "Case Title": "CONSERVATORSHIP OF AURELIA RUIZ *****CASE TRANSFERRED TO SANTA CLARA*****",
      "Court Date": "2014-09-23 09:00 AM",
      "Examiner": "SANDRA HILTON",
      "Calendar Matter": "ACCOUNTING PETITION RE: ACCOUNTING #1, REPORT, FEES",
      "Rulings": "Continued to October 22, 2014. No response to notes prepared 9/8/14. Notes re-faxed to Counsel 9/19/14 at 3:45 p.m.",
      "Judge": "Sandra Hilton"
    },
    {
      "Case Number": "PES13296416",
      "Case Title": "THE ESTATE OF DORA ELIAS KLOTOVICH",
      "Court Date": "2014-09-23 10:30 AM",
      "Examiner": "SANDRA HILTON",
      "Calendar Matter": "Petition Of Pamela Ann Klotovich For Removal Of Administrator Martin L. Klotovich",
      "Rulings": "Hearing. Appearance required.",
      "Judge": "Sandra Hilton"
    },
    {
      "Case Number": "PES13296416",
      "Case Title": "THE ESTATE OF DORA ELIAS KLOTOVICH",
      "Court Date": "2014-09-23 10:30 AM",
      "Examiner": "SANDRA HILTON",
      "Calendar Matter": "ADDED TO CALENDAR FOR Special Letters Of Administration",
      "Rulings": "off calendar",
      "Judge": "Sandra Hilton"
    },
    {
      "Case Number": "PES13296416",
      "Case Title": "THE ESTATE OF DORA ELIAS KLOTOVICH",
      "Court Date": "2014-09-23 10:30 AM",
      "Examiner": "SANDRA HILTON",
      "Calendar Matter": "PETITION FOR LETTERS OF ADMINISTRATION WITH WILL ANNEXED, APPOINTMENT UNDER IAEA",
      "Rulings": "Hearing. Appearance required.",
      "Judge": "Sandra Hilton"
    },
    {
      "Case Number": "PTR13296495",
      "Case Title": "** TRANSFERRED TO ALAMEDA COUNTY ** IN THE MATTER OF THE JUDY YU SPECIAL NEEDS TRUST",
      "Court Date": "2014-09-23 09:00 AM",
      "Examiner": "TRUDY J. VERZOSA",
      "Calendar Matter": "ACCOUNTING PETITION RE: ACCOUNTING #1, REPORT, FEES",
      "Rulings": "Continued to 10/14/14 - Notes faxed 9/19/14",
      "Judge": "Trudy J. Verzosa"
    },
    {
      "Case Number": "PCN13296506",
      "Case Title": "CONSERVATORSHIP OF ARNLJOT KLEIVEN",
      "Court Date": "2014-09-23 09:00 AM",
      "Examiner": "PAMELA MEYERS",
      "Calendar Matter": "ACCOUNTING PETITION RE: REPORT, FEES",
      "Rulings": "petition continued from 9/23 to 10/7",
      "Judge": "Pamela Meyers"
    },
    {
      "Case Number": "PES13296516",
      "Case Title": "THE ESTATE OF LOIS AUDREY HOYER",
      "Court Date": "2014-09-23 09:00 AM",
      "Examiner": "SEAN BANG",
      "Calendar Matter": "ADDED TO CALENDAR FOR Status Of The Estate",
      "Rulings": "Appearance required",
      "Judge": "Sean Bang"
    },
    {
      "Case Number": "PES13296533",
      "Case Title": "THE ESTATE OF ZENAIDA LABASAN TOMAS",
      "Court Date": "2014-09-23 09:00 AM",
      "Examiner": "HELEN TROWBRIDGE",
      "Calendar Matter": "ACCOUNTING PETITION RE: ACCOUNTING #1, REPORT, FEES, FINAL DISTRIBUTION",
      "Rulings": "Continued to 10/7/14. Notes sent.",
      "Judge": "Helen Trowbridge"
    },
    {
      "Case Number": "PCN13296623",
      "Case Title": "CONSERVATORSHIP OF ELIZABETH WRIGHT",
      "Court Date": "2014-09-23 09:00 AM",
      "Examiner": "TRUDY J. VERZOSA",
      "Calendar Matter": "ACCOUNTING PETITION RE: ACCOUNTING #1, REPORT, FEES",
      "Rulings": "Continued to 10/14/14 - Notes emailed 9/19/14",
      "Judge": "Trudy J. Verzosa"
    },
    {
      "Case Number": "PGN13296860",
      "Case Title": "GUARDIANSHIP OF CHRISTOPHER PANG",
      "Court Date": "2014-09-23 09:00 AM",
      "Examiner": "PAMELA MEYERS",
      "Calendar Matter": "FILING OF INVENTORY",
      "Rulings": "status requires an appearance",
      "Judge": "Pamela Meyers"
    },
    {
      "Case Number": "PES13296902",
      "Case Title": "THE ESTATE OF MARILYN A. CEREGHINO",
      "Court Date": "2014-09-23 10:30 AM",
      "Examiner": "PAMELA MEYERS",
      "Calendar Matter": "Petition To Remove Harold Mangar As Executor And Appoint A Special Administrator",
      "Rulings": "continued to 10/21/14",
      "Judge": "Pamela Meyers"
    },
    {
      "Case Number": "PES13296982",
      "Case Title": "THE ESTATE OF KELLY KRISTINE SANDVIG",
      "Court Date": "2014-09-23 09:00 AM",
      "Examiner": "SANDRA HILTON",
      "Calendar Matter": "Petition To Determine Ownership Of Estate Property And For Order Authorizing And Directing Administrator To Transfer Estate Property.",
      "Rulings": "Continued to October 21, 2014 for resolution of notice issues.",
      "Judge": "Sandra Hilton"
    },
    {
      "Case Number": "PES13297157",
      "Case Title": "THE ESTATE OF THOMAS E. HESS",
      "Court Date": "2014-09-23 09:00 AM",
      "Examiner": "SEAN BANG",
      "Calendar Matter": "PETITION FOR SPOUSAL PROPERTY",
      "Rulings": "Appearance required",
      "Judge": "Sean Bang"
    },
    {
      "Case Number": "PCN13297174",
      "Case Title": "CONSERVATORSHIP OF FRANCES L. FOX",
      "Court Date": "2014-09-23 09:00 AM",
      "Examiner": "HELEN TROWBRIDGE",
      "Calendar Matter": "ACCOUNTING PETITION RE: REPORT, FEES",
      "Rulings": "Continued to 10/7/14 at Counsel's request.",
      "Judge": "Helen Trowbridge"
    },
    {
      "Case Number": "PTR13297196",
      "Case Title": "IN RE: THE CHESTER I. FOX AND FRANCES L. FOX 1996 REVOCABLE TRUST",
      "Court Date": "2014-09-23 09:00 AM",
      "Examiner": "HELEN TROWBRIDGE",
      "Calendar Matter": "ACCOUNTING PETITION RE: ACCOUNTING #2, REPORT, FEES",
      "Rulings": "Continued to 10/7/14 at Counsel's request.",
      "Judge": "Helen Trowbridge"
    },
    {
      "Case Number": "PES13297323",
      "Case Title": "THE ESTATE OF JUNE M. HAGLER",
      "Court Date": "2014-09-23 09:00 AM",
      "Examiner": "TRUDY J. VERZOSA",
      "Calendar Matter": "ACCOUNTING PETITION RE: FEES, FINAL DISTRIBUTION",
      "Rulings": "Grant without hearing",
      "Judge": "Trudy J. Verzosa"
    },
    {
      "Case Number": "PES13297348",
      "Case Title": "THE ESTATE OF JOSEPH KEITH",
      "Court Date": "2014-09-23 09:00 AM",
      "Examiner": "PAMELA MEYERS",
      "Calendar Matter": "ACCOUNTING PETITION RE: FEES, FINAL DISTRIBUTION",
      "Rulings": "petition continued to 10/7/14",
      "Judge": "Pamela Meyers"
    },
    {
      "Case Number": "PES14297449",
      "Case Title": "THE ESTATE OF MAURINE S ROBINSON",
      "Court Date": "2014-09-23 09:00 AM",
      "Examiner": "PAMELA MEYERS",
      "Calendar Matter": "ACCOUNTING PETITION RE: REPORT, FEES, FINAL DISTRIBUTION",
      "Rulings": "petition approved; no appearance is required",
      "Judge": "Pamela Meyers"
    },
    {
      "Case Number": "PCN14297453",
      "Case Title": "CONSERVATORSHIP OF LYNDA LIU",
      "Court Date": "2014-09-23 09:00 AM",
      "Examiner": "SEAN BANG",
      "Calendar Matter": "PETITION TO TERMINATE CONSERVATORSHIP OF PERSON AND ESTATE",
      "Rulings": "Grant without appearance",
      "Judge": "Sean Bang"
    },
    {
      "Case Number": "PTR14297482",
      "Case Title": "IN THE MATTER OF THE MICHELLE M. VIGNES TRUST",
      "Court Date": "2014-09-23 09:00 AM",
      "Examiner": "TRUDY J. VERZOSA",
      "Calendar Matter": "Petition For Order Determing Title To Real Property Located At 654 28th, S.F. Ca",
      "Rulings": "Continued to 10/7/14 at request of counsel",
      "Judge": "Trudy J. Verzosa"
    },
    {
      "Case Number": "PES14297487",
      "Case Title": "THE ESTATE OF EUGENE SCHIRADO",
      "Court Date": "2014-09-23 09:00 AM",
      "Examiner": "TRUDY J. VERZOSA",
      "Calendar Matter": "ACCOUNTING PETITION RE: ACCOUNTING #1, REPORT, FEES, FINAL DISTRIBUTION",
      "Rulings": "Grant without hearing",
      "Judge": "Trudy J. Verzosa"
    },
    {
      "Case Number": "PTR14297572",
      "Case Title": "IN THE MATTER OF THE PEARL A. HENNIGH TRUST DTD JUNE 22, 1999, AS AMENDED TRUST",
      "Court Date": "2014-09-23 09:00 AM",
      "Examiner": "TRUDY J. VERZOSA",
      "Calendar Matter": "Petition For Order Clarifying And/Or Modifying Certain Terms Of The Pearl A. Hennigh Trust Dated June 222, 1999, As Amended",
      "Rulings": "Continued to 10/7/14",
      "Judge": "Trudy J. Verzosa"
    },
    {
      "Case Number": "PTR14297572",
      "Case Title": "IN THE MATTER OF THE PEARL A. HENNIGH TRUST DTD JUNE 22, 1999, AS AMENDED TRUST",
      "Court Date": "2014-09-23 09:00 AM",
      "Examiner": "TRUDY J. VERZOSA",
      "Calendar Matter": "Petition For Order (1) Determining Questions Of Construction Of Trust Instrument; (2) Determining Powers And/Or Duties Of Trustee; And, (3) Granting Powers To Trustee",
      "Rulings": "Continued to 10/7/14",
      "Judge": "Trudy J. Verzosa"
    },
    {
      "Case Number": "PES14297644",
      "Case Title": "THE ESTATE OF IRVING F. MIKASES",
      "Court Date": "2014-09-23 09:00 AM",
      "Examiner": "HELEN TROWBRIDGE",
      "Calendar Matter": "Petition To Establish Estate'S Claim Of Ownership To Property, For Breach Of Good Faith And Fair Dealing, For Wrongful Taking Of Estate Property In Bad Faith, And For Order Directing Transfer Of Property To Estate",
      "Rulings": "Continued to 10/7/14. Notes sent.",
      "Judge": "Helen Trowbridge"
    },
    {
      "Case Number": "PTR14297718",
      "Case Title": "IN THE MATTER OF THE SUSAN LEE TRUST",
      "Court Date": "2014-09-23 10:30 AM",
      "Examiner": "SANDRA HILTON",
      "Calendar Matter": "Petition To Compel Trustee To Account And Provide Requested Information",
      "Rulings": "Hearing. Appearance required for Counsel to update the Court on settlement efforts and address how best to proceed. No hearing notes will be sent.",
      "Judge": "Sandra Hilton"
    },
    {
      "Case Number": "PTR14297719",
      "Case Title": "IN RE STEPHEN K. LEE IRREVOCABLE TRUST",
      "Court Date": "2014-09-23 10:30 AM",
      "Examiner": "SANDRA HILTON",
      "Calendar Matter": "Petition To Compel Trustee To Account And Provide Requested Information",
      "Rulings": "Hearing. Appearance required for Counsel to update the Court on settlement efforts and address how best to proceed. No hearing notes will be sent.",
      "Judge": "Sandra Hilton"
    },
    {
      "Case Number": "PTR14297752",
      "Case Title": "IN RE: DONALD E. AND GUADALUPE C. SWARTZ TRUST, DATED MAY 14, 2002",
      "Court Date": "2014-09-23 09:00 AM",
      "Examiner": "HELEN TROWBRIDGE",
      "Calendar Matter": "Petition For Order Confirming Successor Trustee & Transfer Of Trust Real Prop. To Trust Beneficiary",
      "Rulings": "OFF CALENDAR at Counsel's request.",
      "Judge": "Helen Trowbridge"
    },
    {
      "Case Number": "PES14297806",
      "Case Title": "THE ESTATE OF DANIEL JOSEPH COLON",
      "Court Date": "2014-09-23 09:00 AM",
      "Examiner": "SANDRA HILTON",
      "Calendar Matter": "PETITION FOR LETTERS OF ADMINISTRATION",
      "Rulings": "Continued to December 2, 2014 by agreement of Counsel.",
      "Judge": "Sandra Hilton"
    },
    {
      "Case Number": "PES14297865",
      "Case Title": "THE ESTATE OF WILLIAM H COX",
      "Court Date": "2014-09-23 09:00 AM",
      "Examiner": "SANDRA HILTON",
      "Calendar Matter": "ADDED TO CALENDAR FOR Status Of Filing Declaration Re Father'S D.O.B. Or Social Security Number.",
      "Rulings": "off calendar",
      "Judge": "Sandra Hilton"
    },
    {
      "Case Number": "PTR14297906",
      "Case Title": "IN THE MATTER OF THE LAUB REVOCABLE TR. DTD. 1/21/04 AMENDED 8/28/13 TRUST",
      "Court Date": "2014-09-23 10:30 AM",
      "Examiner": "HELEN TROWBRIDGE",
      "Calendar Matter": "Petition To Determine Validity Of Trust.",
      "Rulings": "Continued to 10/7/14. Notes sent.",
      "Judge": "Helen Trowbridge"
    },
    {
      "Case Number": "PTR14297925",
      "Case Title": "IN THE MATTER OF THE MARGARET JANE CARTER TRUST",
      "Court Date": "2014-09-23 09:00 AM",
      "Examiner": "HELEN TROWBRIDGE",
      "Calendar Matter": "Petition For Order Confirming Trust Assets",
      "Rulings": "Grant without hearing",
      "Judge": "Helen Trowbridge"
    },
    {
      "Case Number": "PTR14297928",
      "Case Title": "IN THE MATTER OF THE DOUGLAS P. AMOS GST EXEMPT TRUST, DATED MARCH 24, 2010",
      "Court Date": "2014-09-23 09:00 AM",
      "Examiner": "SEAN BANG",
      "Calendar Matter": "Petition For Acceptance Of Resignation As Trustee And To Appoint Successor Trustee",
      "Rulings": "Continued to 10/7/14",
      "Judge": "Sean Bang"
    },
    {
      "Case Number": "PTR14297928",
      "Case Title": "IN THE MATTER OF THE DOUGLAS P. AMOS GST EXEMPT TRUST, DATED MARCH 24, 2010",
      "Court Date": "2014-09-23 09:00 AM",
      "Examiner": "SEAN BANG",
      "Calendar Matter": "Petition For Order Settling First And Final Account And Report Of Trustee For Douglas P. Amos Gst Ex",
      "Rulings": "Continued to 10/7/14.",
      "Judge": "Sean Bang"
    },
    {
      "Case Number": "PTR14297929",
      "Case Title": "IN THE MATTER OF THE DOUGLAS P. AMOS GST NON-EXEMPT TRUST, DATED 3/24/10",
      "Court Date": "2014-09-23 09:00 AM",
      "Examiner": "SEAN BANG",
      "Calendar Matter": "Petition For Acceptance Of Resignation As Trustee And To Appoint Successor Trustee",
      "Rulings": "Continued to 10/7/14",
      "Judge": "Sean Bang"
    },
    {
      "Case Number": "PTR14297929",
      "Case Title": "IN THE MATTER OF THE DOUGLAS P. AMOS GST NON-EXEMPT TRUST, DATED 3/24/10",
      "Court Date": "2014-09-23 09:00 AM",
      "Examiner": "SEAN BANG",
      "Calendar Matter": "Petition For Order Settling First And Final Account And Report Of Trustee For Douglas P. Amos Gst No",
      "Rulings": "Continued to 10/7/14.",
      "Judge": "Sean Bang"
    },
    {
      "Case Number": "PTR14297930",
      "Case Title": "IN THE MATTER OF THE DONALD J. AMOS GST EXEMPT TRUST, DATED 3/24/10 TRUST",
      "Court Date": "2014-09-23 09:00 AM",
      "Examiner": "SEAN BANG",
      "Calendar Matter": "Petition For Order Settling First And Final Account And Report Of Trustee For Donald J. Amos Gst Exempt Trust",
      "Rulings": "Continued to 10/7/14",
      "Judge": "Sean Bang"
    },
    {
      "Case Number": "PTR14297930",
      "Case Title": "IN THE MATTER OF THE DONALD J. AMOS GST EXEMPT TRUST, DATED 3/24/10 TRUST",
      "Court Date": "2014-09-23 09:00 AM",
      "Examiner": "SEAN BANG",
      "Calendar Matter": "Petition For Acceptance Of Resignation As Trustee And To Appoint Successor Trustee",
      "Rulings": "continued to 10/7/14",
      "Judge": "Sean Bang"
    },
    {
      "Case Number": "PTR14297930",
      "Case Title": "IN THE MATTER OF THE DONALD J. AMOS GST EXEMPT TRUST, DATED 3/24/10 TRUST",
      "Court Date": "2014-09-23 09:00 AM",
      "Examiner": "SEAN BANG",
      "Calendar Matter": "Petition To Modify Irrevocable Trust Based On Changed Circumstances And For Instructions",
      "Rulings": "Continued to 10/7/14",
      "Judge": "Sean Bang"
    },
    {
      "Case Number": "PTR14297931",
      "Case Title": "IN THE MATTER OF THE DONALD J. AMOS GST NON-EXEMPT TRUST, DATE 3/24/10 TRUST",
      "Court Date": "2014-09-23 09:00 AM",
      "Examiner": "SEAN BANG",
      "Calendar Matter": "Petition To Modify Irrevocable Trust Based On Changed Circumstances And For Instructions",
      "Rulings": "Continued to 10/7/14",
      "Judge": "Sean Bang"
    },
    {
      "Case Number": "PTR14297931",
      "Case Title": "IN THE MATTER OF THE DONALD J. AMOS GST NON-EXEMPT TRUST, DATE 3/24/10 TRUST",
      "Court Date": "2014-09-23 09:00 AM",
      "Examiner": "SEAN BANG",
      "Calendar Matter": "Petition For Acceptance Of Resignation As Trustee And To Appoint Successor Trustee",
      "Rulings": "Continued to 10/7/14",
      "Judge": "Sean Bang"
    },
    {
      "Case Number": "PTR14297931",
      "Case Title": "IN THE MATTER OF THE DONALD J. AMOS GST NON-EXEMPT TRUST, DATE 3/24/10 TRUST",
      "Court Date": "2014-09-23 09:00 AM",
      "Examiner": "SEAN BANG",
      "Calendar Matter": "Petition For Order Settling First And Final Account And Report Of Trustee For Donald L. Amos Gst Non-Exempt Trust",
      "Rulings": "Continued to 10/7/14",
      "Judge": "Sean Bang"
    },
    {
      "Case Number": "PES14297957",
      "Case Title": "THE ESTATE OF CAROLINE ZANGANI",
      "Court Date": "2014-09-23 09:00 AM",
      "Examiner": "TRUDY J. VERZOSA",
      "Calendar Matter": "PETITION FOR SPOUSAL PROPERTY",
      "Rulings": "Continued to 10/14/14 - Notes faxed 9/19/14",
      "Judge": "Trudy J. Verzosa"
    },
    {
      "Case Number": "PES14297964",
      "Case Title": "THE ESTATE OF BEATRICE B RAMIREZ",
      "Court Date": "2014-09-23 09:00 AM",
      "Examiner": "HELEN TROWBRIDGE",
      "Calendar Matter": "PETITION FOR LETTERS OF ADMINISTRATION",
      "Rulings": "Continued to 9/30/14 to be heard with PES-14-297861.",
      "Judge": "Helen Trowbridge"
    },
    {
      "Case Number": "PES14297975",
      "Case Title": "THE ESTATE OF MIRTHA E. NAZARIO-LOPEZ",
      "Court Date": "2014-09-23 09:00 AM",
      "Examiner": "SANDRA HILTON",
      "Calendar Matter": "PETITION FOR LETTERS OF ADMINISTRATION",
      "Rulings": "Continued to October 21, 2014 at Counsel's request.",
      "Judge": "Sandra Hilton"
    },
    {
      "Case Number": "PES14297983",
      "Case Title": "THE ESTATE OF THERESA MARGARET DONAHUE",
      "Court Date": "2014-09-23 09:00 AM",
      "Examiner": "PAMELA MEYERS",
      "Calendar Matter": "PETITION FOR LETTERS OF ADMINISTRATION",
      "Rulings": "petition continued to 10/14/14",
      "Judge": "Pamela Meyers"
    },
    {
      "Case Number": "PES14297996",
      "Case Title": "THE ESTATE OF DEINSE ALISON CASSINELLI",
      "Court Date": "2014-09-23 09:00 AM",
      "Examiner": "HELEN TROWBRIDGE",
      "Calendar Matter": "PETITION FOR LETTERS OF ADMINISTRATION",
      "Rulings": "Grant without hearing",
      "Judge": "Helen Trowbridge"
    },
    {
      "Case Number": "PES14297999",
      "Case Title": "THE ESTATE OF JON HENRY KOUBA",
      "Court Date": "2014-09-23 09:00 AM",
      "Examiner": "TRUDY J. VERZOSA",
      "Calendar Matter": "PETITION FOR PROBATE OF WILL AND FOR LETTERS TESTAMENTARY",
      "Rulings": "Continued to 10/7/14 - The Supplement filed 9/19/14 does not provide the information required by the last sentence of LRSF 14.27.D.1.",
      "Judge": "Trudy J. Verzosa"
    },
    {
      "Case Number": "PES14298007",
      "Case Title": "THE ESTATE OF SUI FONG MA LEE",
      "Court Date": "2014-09-23 09:00 AM",
      "Examiner": "SANDRA HILTON",
      "Calendar Matter": "PETITION FOR SPOUSAL PROPERTY",
      "Rulings": "Continued to September 29, 2014 to correct calendaring error.",
      "Judge": "Sandra Hilton"
    }
  ],
  "_date": "2014-09-23"
}