{
  "department": "204",
  "calendar_kind": null,
  "scraped_at": "2026-05-03T18:38:15.181Z",
  "source_url": "https://webapps.sftc.org/tr/tr.dll?RulingID=7&SessionID=E90B57BAB30D063200956EAE7087786AD68A4460",
  "reported_total": 81,
  "rulings": [
    {
      "Case Number": "PCN91168121",
      "Case Title": "CONS. OF FRANCES RITA VELLA",
      "Court Date": "2017-10-16 09:00 AM",
      "Examiner": "SANDRA HILTON",
      "Calendar Matter": "ADDED TO CALENDAR FOR Status On Filing Of A Petition To Terminate Conservatorship",
      "Rulings": "off calendar. no appearance required.",
      "Judge": "Sandra Hilton"
    },
    {
      "Case Number": "PES81230056",
      "Case Title": "THE ESTATE OF OTTO C. STELLING",
      "Court Date": "2017-10-16 09:00 AM",
      "Examiner": "SANDRA HILTON",
      "Calendar Matter": "ADDED TO CALENDAR FOR Status For Filing Inventory And Appraisal And For Close Of Estate",
      "Rulings": "off calendar",
      "Judge": "Sandra Hilton"
    },
    {
      "Case Number": "PCN03284706",
      "Case Title": "CONSERVATORSHIP OF JANE PRICE WEAVER",
      "Court Date": "2017-10-16 09:00 AM",
      "Examiner": "SEAN BANG",
      "Calendar Matter": "ACCOUNTING PETITION RE: ACCOUNTING #7, REPORT, FEES",
      "Rulings": "Continued to 12/4/17 to be heard with trust matter.",
      "Judge": "Sean Bang"
    },
    {
      "Case Number": "PCN03285206",
      "Case Title": "CONSERVATORSHIP OF JOHN THOMAS CONNELL",
      "Court Date": "2017-10-16 09:00 AM",
      "Examiner": "TIMOTHY KNEIS",
      "Calendar Matter": "ACCOUNTING PETITION RE: ACCOUNTING #7, REPORT, FEES",
      "Rulings": "Grant without hearing",
      "Judge": "Timothy Kneis"
    },
    {
      "Case Number": "PCN03285324",
      "Case Title": "CONSERVATORSHIP OF WILL FRIDLIN JR.",
      "Court Date": "2017-10-16 09:00 AM",
      "Examiner": "TIMOTHY KNEIS",
      "Calendar Matter": "ADDED TO CALENDAR FOR Status For Filing Of Petition To Terminate Conservatorship And On Waiver Of Accounting Due To The Death Of The Conservatee",
      "Rulings": "Off calendar",
      "Judge": "Timothy Kneis"
    },
    {
      "Case Number": "PTR05287797",
      "Case Title": "IN THE MATTER OF THE SHIRLEY LINCHNER 1998 SPECIAL NEEDS TRUST",
      "Court Date": "2017-10-16 09:00 AM",
      "Examiner": "HELEN TROWBRIDGE",
      "Calendar Matter": "ACCOUNTING PETITION RE: ACCOUNTING #1, REPORT, FEES",
      "Rulings": "Grant without hearing",
      "Judge": "Helen Trowbridge"
    },
    {
      "Case Number": "PTR07289706",
      "Case Title": "IN THE MATTER OF THE BESSIE B. DEDEAUX TRUST",
      "Court Date": "2017-10-16 09:00 AM",
      "Examiner": "TIMOTHY KNEIS",
      "Calendar Matter": "ACCOUNTING PETITION RE: ACCOUNTING #6, REPORT, FEES",
      "Rulings": "Continued to 11/6/17",
      "Judge": "Timothy Kneis"
    },
    {
      "Case Number": "PTR07290391",
      "Case Title": "IN THE MATTER OF THE NANCY A. SEELA TRUST",
      "Court Date": "2017-10-16 09:00 AM",
      "Examiner": "HELEN TROWBRIDGE",
      "Calendar Matter": "FUTURE ACCOUNTING",
      "Rulings": "Hearing. Appearance required.",
      "Judge": "Helen Trowbridge"
    },
    {
      "Case Number": "PCN08291252",
      "Case Title": "**TRANSFERRED TO SONOMA COUNTY** CONSERVATORSHIP OF MICHAEL LAZZARI",
      "Court Date": "2017-10-16 09:00 AM",
      "Examiner": "SEAN BANG",
      "Calendar Matter": "ACCOUNTING PETITION RE: ACCOUNTING #4, REPORT, FEES",
      "Rulings": "Continued to 11/13/17 at request of counsel.",
      "Judge": "Sean Bang"
    },
    {
      "Case Number": "PTR09292308",
      "Case Title": "IN THE MATTER OF THE DOROTHY S. RABKIN TRUST",
      "Court Date": "2017-10-16 09:00 AM",
      "Examiner": "TRUDY J. VERZOSA",
      "Calendar Matter": "ACCOUNTING PETITION RE: ACCOUNTING #2, REPORT, FEES",
      "Rulings": "Continued to 10/30/17 due to voluminous pleadings - appearance will be required on that date. Court to determine whether all interested parties have received proper notice. If so, the remaining issues will be heard on 10/30/17. If not, the matter will be continued for proper notice.",
      "Judge": "Trudy J. Verzosa"
    },
    {
      "Case Number": "PTR09292779",
      "Case Title": "IN THE MATTER OF THE NICOLE HUSTED SPECIAL NEEDS TRUST",
      "Court Date": "2017-10-16 09:00 AM",
      "Examiner": "SEAN BANG",
      "Calendar Matter": "ACCOUNTING PETITION RE: ACCOUNTING #4, REPORT, FEES, FINAL DISTRIBUTION",
      "Rulings": "Appearance required.",
      "Judge": "Sean Bang"
    },
    {
      "Case Number": "PCN09292813",
      "Case Title": "CONSERVATORSHIP OF TOM WUETRICH",
      "Court Date": "2017-10-16 09:00 AM",
      "Examiner": "HELEN TROWBRIDGE",
      "Calendar Matter": "ADDED TO CALENDAR FOR Status For Filing Of Petition To Terminate Conservatorship And On Waiver Of Accounting Due To The Death Of The Conservatee",
      "Rulings": "Continued to 11/13/17 at Counsel's request.",
      "Judge": "Helen Trowbridge"
    },
    {
      "Case Number": "PES09293011",
      "Case Title": "THE ESTATE OF KYOKO U WARD",
      "Court Date": "2017-10-16 09:00 AM",
      "Examiner": "TRUDY J. VERZOSA",
      "Calendar Matter": "ACCOUNTING PETITION RE: ACCOUNTING #2, REPORT",
      "Rulings": "Continued to 10/30/17 for filing of account statements.",
      "Judge": "Trudy J. Verzosa"
    },
    {
      "Case Number": "PES11294599",
      "Case Title": "THE ESTATE OF CLARITA MARIA FAZZARI",
      "Court Date": "2017-10-16 09:00 AM",
      "Examiner": "TRUDY J. VERZOSA",
      "Calendar Matter": "PROBATE ACCOUNTING STATUS PETITION",
      "Rulings": "Continued to 11/6/17 - Notes emailed 10/12/17",
      "Judge": "Trudy J. Verzosa"
    },
    {
      "Case Number": "PCN11294809",
      "Case Title": "CONSERVATORSHIP OF ARNELLA FLEMING",
      "Court Date": "2017-10-16 09:00 AM",
      "Examiner": "TRUDY J. VERZOSA",
      "Calendar Matter": "ACCOUNTING PETITION RE: ACCOUNTING #3, REPORT, FEES",
      "Rulings": "Continued to 11/13/17 at request of counsel",
      "Judge": "Trudy J. Verzosa"
    },
    {
      "Case Number": "PCN11294957",
      "Case Title": "CONSERVATORSHIP OF EDWARD LEONG WAY",
      "Court Date": "2017-10-16 09:00 AM",
      "Examiner": "SANDRA HILTON",
      "Calendar Matter": "ADDED TO CALENDAR FOR Status For Filing Of Petition To Terminate Conservatorship And Of The Final Accounting Due To The Death Of The Conservatee",
      "Rulings": "continued to november 13, 2017, at counsel's request.",
      "Judge": "Sandra Hilton"
    },
    {
      "Case Number": "PES11295132",
      "Case Title": "THE ESTATE OF MARTHA SANCHEZ",
      "Court Date": "2017-10-16 09:00 AM",
      "Examiner": "HELEN TROWBRIDGE",
      "Calendar Matter": "ADDED TO CALENDAR FOR Status On Close Of Estate",
      "Rulings": "Hearing. Appearance required.",
      "Judge": "Helen Trowbridge"
    },
    {
      "Case Number": "PCN11295240",
      "Case Title": "CONSERVATORSHIP OF WAH LUM HONG",
      "Court Date": "2017-10-16 09:00 AM",
      "Examiner": "HELEN TROWBRIDGE",
      "Calendar Matter": "ACCOUNTING PETITION RE: ACCOUNTING, REPORT, FEES",
      "Rulings": "Grant without hearing",
      "Judge": "Helen Trowbridge"
    },
    {
      "Case Number": "PCN12295409",
      "Case Title": "CONSERVATORSHIP OF MARILYN SILVERMAN-BALLONOFF",
      "Court Date": "2017-10-16 09:00 AM",
      "Examiner": "TRUDY J. VERZOSA",
      "Calendar Matter": "Petition For Litigation Attorneys Fees And Costs And Authority Ti Pay Litigation Counsel Fees And Costs",
      "Rulings": "Continued to 10/30/17 - please submit order",
      "Judge": "Trudy J. Verzosa"
    },
    {
      "Case Number": "PTR12295661",
      "Case Title": "IN THE MATTER OF THE TRUDY SACHS TRUST",
      "Court Date": "2017-10-16 09:00 AM",
      "Examiner": "TRUDY J. VERZOSA",
      "Calendar Matter": "FUTURE ACCOUNTING",
      "Rulings": "Off calendar",
      "Judge": "Trudy J. Verzosa"
    },
    {
      "Case Number": "PCN12296085",
      "Case Title": "CONSERVATORSHIP OF ANNE MEDIC",
      "Court Date": "2017-10-16 09:00 AM",
      "Examiner": "TRUDY J. VERZOSA",
      "Calendar Matter": "ADDED TO CALENDAR FOR Status Of Petition To Terminate Conservatorship And Of The Final Accounting Due To The Death Of The Conservatee",
      "Rulings": "Appearance required",
      "Judge": "Trudy J. Verzosa"
    },
    {
      "Case Number": "PTR13296491",
      "Case Title": "***TRANSFERRED TO SANTA BARBARA COUNTY*** IN THE MATTER OF THE JOAN KELLEY-RYDER TRUST, AS AMENDED AND RESTATED",
      "Court Date": "2017-10-16 09:00 AM",
      "Examiner": "SANDRA HILTON",
      "Calendar Matter": "Petition For Authorization To Obtain Loan Secured By Trust Rental Property To Pay Liabilities Of Trust And For An Additional Reserve",
      "Rulings": "grant without hearing.",
      "Judge": "Sandra Hilton"
    },
    {
      "Case Number": "PCN13297063",
      "Case Title": "CONSERVATORSHIP OF ORA GOSEY",
      "Court Date": "2017-10-16 09:00 AM",
      "Examiner": "TRUDY J. VERZOSA",
      "Calendar Matter": "ADDED TO CALENDAR FOR Status For Filing Of Petition To Terminate Conservatorship And Of The Final Accounting Due To The Death Of The Conservatee",
      "Rulings": "Continued to 11/13/17 at request of counsel",
      "Judge": "Trudy J. Verzosa"
    },
    {
      "Case Number": "PES13297378",
      "Case Title": "THE ESTATE OF KENNETH DOUGLAS THOMSON",
      "Court Date": "2017-10-16 09:00 AM",
      "Examiner": "TRUDY J. VERZOSA",
      "Calendar Matter": "ACCOUNTING PETITION RE: ACCOUNTING #2, REPORT, FEES, FINAL DISTRIBUTION",
      "Rulings": "Grant without hearing",
      "Judge": "Trudy J. Verzosa"
    },
    {
      "Case Number": "PGN14297438",
      "Case Title": "***TRANSFERRED TO ALAMEDA COUNTY***GUARDIANSHIP OF DANIEL JOSEPH COLON JR",
      "Court Date": "2017-10-16 09:00 AM",
      "Examiner": "TIMOTHY KNEIS",
      "Calendar Matter": "ADDED TO CALENDAR FOR Status On Transfer To Alameda County",
      "Rulings": "Continued to 11/6/17",
      "Judge": "Timothy Kneis"
    },
    {
      "Case Number": "PCN14297447",
      "Case Title": "CONSERVATORSHIP OF MARIE K. HOM",
      "Court Date": "2017-10-16 09:00 AM",
      "Examiner": "HELEN TROWBRIDGE",
      "Calendar Matter": "Petition To Pay Fees And Additional Retainer To Litigation Counsel",
      "Rulings": "Hearing. Appearance required.",
      "Judge": "Helen Trowbridge"
    },
    {
      "Case Number": "PCN14297602",
      "Case Title": "CONSERVATORSHIP OF NORMA MOGANNAM",
      "Court Date": "2017-10-16 09:00 AM",
      "Examiner": "SANDRA HILTON",
      "Calendar Matter": "FUTURE ACCOUNTING",
      "Rulings": "continued to october 30, 2017 due to special circumstances (fire).",
      "Judge": "Sandra Hilton"
    },
    {
      "Case Number": "PES14297695",
      "Case Title": "THE ESTATE OF ROLAND WILLIAM HINNERS",
      "Court Date": "2017-10-16 09:00 AM",
      "Examiner": "SANDRA HILTON",
      "Calendar Matter": "ACCOUNTING PETITION RE: ACCOUNTING #1, REPORT, FINAL DISTRIBUTION",
      "Rulings": "continued to december 4, 2017 to be after the petition to remove co-personal representative.",
      "Judge": "Sandra Hilton"
    },
    {
      "Case Number": "PTR14297819",
      "Case Title": "IN RE: THE REGINALD BURKE LUCAS REVOCABLE TRUST ESTABLISH",
      "Court Date": "2017-10-16 09:00 AM",
      "Examiner": "HELEN TROWBRIDGE",
      "Calendar Matter": "FUTURE ACCOUNTING",
      "Rulings": "Hearing. Appearance required.",
      "Judge": "Helen Trowbridge"
    },
    {
      "Case Number": "PTR14298017",
      "Case Title": "IN RE: THE JANE PRICE WEAVER 2014 REVOCABLE TRUST",
      "Court Date": "2017-10-16 09:00 AM",
      "Examiner": "SEAN BANG",
      "Calendar Matter": "ACCOUNTING PETITION RE: ACCOUNTING #2, REPORT, FEES",
      "Rulings": "Continued to 12/4/17 at request of counsel.",
      "Judge": "Sean Bang"
    },
    {
      "Case Number": "PES15298525",
      "Case Title": "THE ESTATE OF ANGEL A SOCARRAS",
      "Court Date": "2017-10-16 09:00 AM",
      "Examiner": "TIMOTHY KNEIS",
      "Calendar Matter": "ACCOUNTING PETITION RE: ACCOUNTING #1, REPORT, FEES, FINAL DISTRIBUTION",
      "Rulings": "Continued to 11/6/17",
      "Judge": "Timothy Kneis"
    },
    {
      "Case Number": "PES15298529",
      "Case Title": "THE ESTATE OF THOMAS FENNNER DALLMAN",
      "Court Date": "2017-10-16 09:00 AM",
      "Examiner": "TRUDY J. VERZOSA",
      "Calendar Matter": "ACCOUNTING PETITION RE: ACCOUNTING, REPORT, FINAL DISTRIBUTION",
      "Rulings": "Appearance required",
      "Judge": "Trudy J. Verzosa"
    },
    {
      "Case Number": "PES15298668",
      "Case Title": "THE ESTATE OF BRIGIDA JUBILO CUSTODIA",
      "Court Date": "2017-10-16 09:00 AM",
      "Examiner": "SANDRA HILTON",
      "Calendar Matter": "ACCOUNTING PETITION RE: REPORT, FEES, FINAL DISTRIBUTION",
      "Rulings": "continued to october 30, 2017 to be heard by Judge Stewart.",
      "Judge": "Sandra Hilton"
    },
    {
      "Case Number": "PTR15299007",
      "Case Title": "IN THE MATTER OF THE LOWE FAMILY TRUST, EST. OCT 1, 1992 TRUST",
      "Court Date": "2017-10-16 09:00 AM",
      "Examiner": "HELEN TROWBRIDGE",
      "Calendar Matter": "Petition To Allow First Forensic Accounting Of Successor Co-Trustees For The Period September 2, 2014 To February 27, 2015, And For Approval Of Payment To Forensic Accountant For Services Rendered",
      "Rulings": "Hearing. Appearance required.",
      "Judge": "Helen Trowbridge"
    },
    {
      "Case Number": "PES15299020",
      "Case Title": "THE ESTATE OF MARIE ANTOINETTE HACKETT",
      "Court Date": "2017-10-16 09:00 AM",
      "Examiner": "HELEN TROWBRIDGE",
      "Calendar Matter": "ADDED TO CALENDAR FOR Filing Of The Account And Petition For Final Distribution",
      "Rulings": "OFF CALENDAR. Duplicate entry.",
      "Judge": "Helen Trowbridge"
    },
    {
      "Case Number": "PES15299020",
      "Case Title": "THE ESTATE OF MARIE ANTOINETTE HACKETT",
      "Court Date": "2017-10-16 09:00 AM",
      "Examiner": "HELEN TROWBRIDGE",
      "Calendar Matter": "ADDED TO CALENDAR FOR Status Of Closing Estate",
      "Rulings": "Hearing. Appearance required.",
      "Judge": "Helen Trowbridge"
    },
    {
      "Case Number": "PTR15299091",
      "Case Title": "IN THE MATTER OF THE TRUST CREATED UNDER THE WILL OF WALTER HICKS TRUST",
      "Court Date": "2017-10-16 09:00 AM",
      "Examiner": "HELEN TROWBRIDGE",
      "Calendar Matter": "ACCOUNTING PETITION RE: ACCOUNTING #11, REPORT, FEES",
      "Rulings": "Grant without hearing",
      "Judge": "Helen Trowbridge"
    },
    {
      "Case Number": "PES15299154",
      "Case Title": "THE ESTATE OF FRANKLIN YEE",
      "Court Date": "2017-10-16 09:00 AM",
      "Examiner": "SEAN BANG",
      "Calendar Matter": "PROBATE ACCOUNTING STATUS PETITION",
      "Rulings": "Grant without hearing.",
      "Judge": "Sean Bang"
    },
    {
      "Case Number": "PES15299169",
      "Case Title": "THE ESTATE OF VERA TUCKER",
      "Court Date": "2017-10-16 09:00 AM",
      "Examiner": "TIMOTHY KNEIS",
      "Calendar Matter": "ACCOUNTING PETITION RE: FEES, FINAL DISTRIBUTION",
      "Rulings": "Final continuance to 11/13/17 (still not response to Examiner's Notes of 7/20/17).",
      "Judge": "Timothy Kneis"
    },
    {
      "Case Number": "PES15299215",
      "Case Title": "THE ESTATE OF MORADA B. RAMOS",
      "Court Date": "2017-10-16 09:00 AM",
      "Examiner": "SANDRA HILTON",
      "Calendar Matter": "ADDED TO CALENDAR FOR Status On Close Of Estate",
      "Rulings": "continued to november 13, 2017. no later than Wednesday, november 8, 2017, the PR must file either a Petition for Final Distribution or a Petition to Approve Status of Administration. Appearance required on 11/13/17 if no petition is filed.",
      "Judge": "Sandra Hilton"
    },
    {
      "Case Number": "PES15299265",
      "Case Title": "THE ESTATE OF CLARENCE HANKINS",
      "Court Date": "2017-10-16 09:00 AM",
      "Examiner": "SEAN BANG",
      "Calendar Matter": "Notice Of Motion And Motion To Be Relieved As Counsel",
      "Rulings": "Continued to 11/20/17. Filed stamped courtesy copy of petition and related documents, along with proposed order, have not been received.",
      "Judge": "Sean Bang"
    },
    {
      "Case Number": "PGN15299359",
      "Case Title": "GUARDIANSHIP OF NICOLE PETERSEN",
      "Court Date": "2017-10-16 09:00 AM",
      "Examiner": "SEAN BANG",
      "Calendar Matter": "ACCOUNTING PETITION RE: ACCOUNTING",
      "Rulings": "Continued to 10/23/17 for submission of proposed order.",
      "Judge": "Sean Bang"
    },
    {
      "Case Number": "PES15299383",
      "Case Title": "THE ESTATE OF YUAN SOON CHANG",
      "Court Date": "2017-10-16 09:00 AM",
      "Examiner": "SANDRA HILTON",
      "Calendar Matter": "PROBATE ACCOUNTING STATUS PETITION",
      "Rulings": "grant without hearing. petition for final distribution must be filed no later than 1/16/18. appearance required on 1/22/16 if not filed.",
      "Judge": "Sandra Hilton"
    },
    {
      "Case Number": "PCN15299384",
      "Case Title": "CONSERVATORSHIP OF DAN THOMAS MCDONALD",
      "Court Date": "2017-10-16 09:00 AM",
      "Examiner": "SEAN BANG",
      "Calendar Matter": "PETITION TO TERMINATE CONSERVATORSHIP OF PERSON AND ESTATE",
      "Rulings": "Continued to 11/13/17 for failure to file declaration and provide revised proposed order.",
      "Judge": "Sean Bang"
    },
    {
      "Case Number": "PES16299413",
      "Case Title": "THE ESTATE OF VENRICE PALMER",
      "Court Date": "2017-10-16 09:00 AM",
      "Examiner": "TIMOTHY KNEIS",
      "Calendar Matter": "ADDED TO CALENDAR FOR Status On Close Of Estate",
      "Rulings": "Hearing-Appearance required.",
      "Judge": "Timothy Kneis"
    },
    {
      "Case Number": "PES16299473",
      "Case Title": "THE ESTATE OF KENNETH WAYNE LARSON SR",
      "Court Date": "2017-10-16 09:00 AM",
      "Examiner": "TIMOTHY KNEIS",
      "Calendar Matter": "PROBATE ACCOUNTING STATUS PETITION",
      "Rulings": "Continued to 11/6/17",
      "Judge": "Timothy Kneis"
    },
    {
      "Case Number": "PES16299520",
      "Case Title": "THE ESTATE OF DIANA L DELONZOR",
      "Court Date": "2017-10-16 09:00 AM",
      "Examiner": "TRUDY J. VERZOSA",
      "Calendar Matter": "ACCOUNTING PETITION RE: FINAL DISTRIBUTION",
      "Rulings": "Granted without hearing. Order revised to deduct the $500 reserve from the assets on hand per Petition (cash of $854.17).",
      "Judge": "Trudy J. Verzosa"
    },
    {
      "Case Number": "PES16299526",
      "Case Title": "THE ESTATE OF VASILIKI BETTY CHERIN",
      "Court Date": "2017-10-16 09:00 AM",
      "Examiner": "SANDRA HILTON",
      "Calendar Matter": "ADDED TO CALENDAR FOR Status On The Reserve",
      "Rulings": "off calendar",
      "Judge": "Sandra Hilton"
    },
    {
      "Case Number": "PES16299529",
      "Case Title": "THE ESTATE OF AGNES YAO",
      "Court Date": "2017-10-16 09:00 AM",
      "Examiner": "HELEN TROWBRIDGE",
      "Calendar Matter": "ACCOUNTING PETITION RE: REPORT, FEES, FINAL DISTRIBUTION",
      "Rulings": "Grant without hearing",
      "Judge": "Helen Trowbridge"
    },
    {
      "Case Number": "PES16299540",
      "Case Title": "THE ESTATE OF ALVIN WONG",
      "Court Date": "2017-10-16 09:00 AM",
      "Examiner": "SEAN BANG",
      "Calendar Matter": "ADDED TO CALENDAR FOR Status On Close Of Estate",
      "Rulings": "off calendar.",
      "Judge": "Sean Bang"
    },
    {
      "Case Number": "PES16299554",
      "Case Title": "THE ESTATE OF MARLEEN F. VAN KAMMEN",
      "Court Date": "2017-10-16 09:00 AM",
      "Examiner": "TIMOTHY KNEIS",
      "Calendar Matter": "ADDED TO CALENDAR FOR Status On Close Of Estate",
      "Rulings": "Continued to 11/13/17",
      "Judge": "Timothy Kneis"
    },
    {
      "Case Number": "PGN16299577",
      "Case Title": "GUARDIANSHIP OF AIJNOS NOCOS MCFARLAND",
      "Court Date": "2017-10-16 09:00 AM",
      "Examiner": "SANDRA HILTON",
      "Calendar Matter": "Petition For Approval Of Mediation Agreement",
      "Rulings": "continued to october 18, 2017 to be heard by Judge Stewart, who previously ordered approval of this agreement required a noticed hearing.",
      "Judge": "Sandra Hilton"
    },
    {
      "Case Number": "PES16299578",
      "Case Title": "THE ESTATE OF MARY ELIZABETH YOAKUM-DAVIS",
      "Court Date": "2017-10-16 09:00 AM",
      "Examiner": "SEAN BANG",
      "Calendar Matter": "ADDED TO CALENDAR FOR Status On Close Of Estate",
      "Rulings": "off calendar.",
      "Judge": "Sean Bang"
    },
    {
      "Case Number": "PTR16299858",
      "Case Title": "IN THE MATTER OF THE THE BLANDINA D. PADLAN REVOCABLE TRUST OF 5/16/00 TRUST",
      "Court Date": "2017-10-16 09:00 AM",
      "Examiner": "TRUDY J. VERZOSA",
      "Calendar Matter": "Petition To 1) Subject Trust To Probate Court Supervision; 2) Remove Trustee, Appoint Successor Trustee; 3) Compel Accounting; 4) Authorize Payment Of",
      "Rulings": "Continued to 11/27/17 to be heard with accounting",
      "Judge": "Trudy J. Verzosa"
    },
    {
      "Case Number": "PES16300253",
      "Case Title": "THE ESTATE OF DAISY M. TURNER",
      "Court Date": "2017-10-16 09:00 AM",
      "Examiner": "SANDRA HILTON",
      "Calendar Matter": "ACCOUNTING PETITION RE: REPORT, FEES, FINAL DISTRIBUTION",
      "Rulings": "continued to october 30, 2017 for a response to the examiner notes, emailed to counsel on 10/11/17 at 3:40 p.m.",
      "Judge": "Sandra Hilton"
    },
    {
      "Case Number": "PES16300283",
      "Case Title": "THE ESTATE OF CHAI KWAI LOO",
      "Court Date": "2017-10-16 09:00 AM",
      "Examiner": "TRUDY J. VERZOSA",
      "Calendar Matter": "Petition By Executors To Establish Estates Claim Of Ownership To Properties And For Order Directing Their Transfer To And From Estate",
      "Rulings": "Continued to 10/30/17 - Notes emailed 10/12/17",
      "Judge": "Trudy J. Verzosa"
    },
    {
      "Case Number": "PCN16300340",
      "Case Title": "CONSERVATORSHIP OF MARK CARRAHER",
      "Court Date": "2017-10-16 09:00 AM",
      "Examiner": "TRUDY J. VERZOSA",
      "Calendar Matter": "ADDED TO CALENDAR FOR Status For Filing Of Petition To Terminate Conservatorship And Of The Final Accounting Due To The Death Of The Conservatee",
      "Rulings": "OFF CALENDAR",
      "Judge": "Trudy J. Verzosa"
    },
    {
      "Case Number": "PCN16300417",
      "Case Title": "CONSERVATORSHIP OF DONATELLA MARIA MARTINELLI",
      "Court Date": "2017-10-16 09:00 AM",
      "Examiner": "TRUDY J. VERZOSA",
      "Calendar Matter": "Petition For Substituted Judgment For Authority To Establish A First Party Pooled Special Needs Trust Account For The Benefit Of Conservatee; Authorizing Trustee'S Fees; And Setting Trustee'S Bond",
      "Rulings": "Continued to 11/6/17 - Notes faxed 10/12/17",
      "Judge": "Trudy J. Verzosa"
    },
    {
      "Case Number": "PES16300429",
      "Case Title": "THE ESTATE OF JESSIE WALTON",
      "Court Date": "2017-10-16 09:00 AM",
      "Examiner": "HELEN TROWBRIDGE",
      "Calendar Matter": "ACCOUNTING PETITION RE: ACCOUNTING, REPORT, FEES, FINAL DISTRIBUTION",
      "Rulings": "Continued to 12/11/17 for petition to be amended.",
      "Judge": "Helen Trowbridge"
    },
    {
      "Case Number": "PES16300454",
      "Case Title": "THE ESTATE OF ZARA D. ABRAHAM",
      "Court Date": "2017-10-16 09:00 AM",
      "Examiner": "SANDRA HILTON",
      "Calendar Matter": "PETITION FOR SPOUSAL PROPERTY",
      "Rulings": "continued to january 8, 2018 to follow the petition to determine inheritance rights filed in the related estate.",
      "Judge": "Sandra Hilton"
    },
    {
      "Case Number": "PES17300484",
      "Case Title": "THE ESTATE OF GALINA SHAMBO",
      "Court Date": "2017-10-16 09:00 AM",
      "Examiner": "SANDRA HILTON",
      "Calendar Matter": "ACCOUNTING PETITION RE: ACCOUNTING, REPORT, FEES, FINAL DISTRIBUTION",
      "Rulings": "grant without hearing",
      "Judge": "Sandra Hilton"
    },
    {
      "Case Number": "PES17300714",
      "Case Title": "THE ESTATE OF ROSA ISABEL VALLE",
      "Court Date": "2017-10-16 09:00 AM",
      "Examiner": "HELEN TROWBRIDGE",
      "Calendar Matter": "PETITION FOR PROBATE OF WILL AND FOR LETTERS TESTAMENTARY, APPOINTMENT UNDER IAEA",
      "Rulings": "Continued to 11/6/17. Notes sent.",
      "Judge": "Helen Trowbridge"
    },
    {
      "Case Number": "PES17300737",
      "Case Title": "THE ESTATE OF DEAN MARIO TREFAULT",
      "Court Date": "2017-10-16 09:00 AM",
      "Examiner": "SEAN BANG",
      "Calendar Matter": "PETITION FOR LETTERS OF ADMINISTRATION",
      "Rulings": "Continued to 11/13/17 to be heard with competing petition.",
      "Judge": "Sean Bang"
    },
    {
      "Case Number": "PES17300737",
      "Case Title": "THE ESTATE OF DEAN MARIO TREFAULT",
      "Court Date": "2017-10-16 09:00 AM",
      "Examiner": "SEAN BANG",
      "Calendar Matter": "PETITION FOR PROBATE OF WILL AND FOR LETTERS TESTAMENTARY, APPOINTMENT UNDER IAEA",
      "Rulings": "Continued to 11/13/17. All issues raised in Examiner's Notes dated 9/14/17 have not been addressed. Courtesy copy of any filed document required by 11/6/17.",
      "Judge": "Sean Bang"
    },
    {
      "Case Number": "PTR17300816",
      "Case Title": "IN THE MATTER OF THE THE W AND S LOUIE FAMILY TRUST",
      "Court Date": "2017-10-16 09:00 AM",
      "Examiner": "TRUDY J. VERZOSA",
      "Calendar Matter": "First Account (5/23/14-12/31/16) And Petition For Settlement Of Account And Approval And Payment Of Attorney'S Fees And Costs",
      "Rulings": "Continued to 10/23/17 - appearance will be required on that date",
      "Judge": "Trudy J. Verzosa"
    },
    {
      "Case Number": "PTR17300829",
      "Case Title": "IN THE MATTER OF THE TIEN 1992 FAMILY TRUST",
      "Court Date": "2017-10-16 09:00 AM",
      "Examiner": "TRUDY J. VERZOSA",
      "Calendar Matter": "Petition To Compel Distribution To Beneficiaries",
      "Rulings": "Continued to 10/30/17 - Judge Stewart will not take the bench on 10/16/17. Appearance will be required on 10/30/17.",
      "Judge": "Trudy J. Verzosa"
    },
    {
      "Case Number": "PTR17300838",
      "Case Title": "IN THE MATTER OF THE LEW FAMILY TRUST, DATED OCTOBER 25, 1989 TRUST",
      "Court Date": "2017-10-16 09:00 AM",
      "Examiner": "SANDRA HILTON",
      "Calendar Matter": "Petition For An Order (1) Compelling Administration And Final Distribution Of The Lew Family Trust Dated October 25, 1989; (2) Redressing Respondent A",
      "Rulings": "continued to january ?, 2018 by agreement of counsel, to be after the demurrer, now continued to 12/20/17.",
      "Judge": "Sandra Hilton"
    },
    {
      "Case Number": "PTR17300864",
      "Case Title": "** TRANSFERRED TO SAN MATEO ** IN THE MATTER OF THE THE 2005 KERSTIN WESTERSTAHL TRUST, AS AMENDED TRUST",
      "Court Date": "2017-10-16 09:00 AM",
      "Examiner": "SANDRA HILTON",
      "Calendar Matter": "FILING OF INVENTORY",
      "Rulings": "off calendar",
      "Judge": "Sandra Hilton"
    },
    {
      "Case Number": "PES17300964",
      "Case Title": "THE ESTATE OF RITA C. EMELIA MCLINN",
      "Court Date": "2017-10-16 09:00 AM",
      "Examiner": "TIMOTHY KNEIS",
      "Calendar Matter": "PETITION FOR PROBATE OF WILL AND FOR LETTERS TESTAMENTARY",
      "Rulings": "Hearing.",
      "Judge": "Timothy Kneis"
    },
    {
      "Case Number": "PTR17301034",
      "Case Title": "***TRANSFERRED TO ALAMEDA COUNTY***IN THE MATTER OF THE THE MAYA VIZZI SETTLEMENT TRUST",
      "Court Date": "2017-10-16 09:00 AM",
      "Examiner": "TRUDY J. VERZOSA",
      "Calendar Matter": "Petition To Establish Minor'S Settlement Trust; Bring Trust Under Continuing Jurisdiction Of Alameda",
      "Rulings": "Grant without hearing",
      "Judge": "Trudy J. Verzosa"
    },
    {
      "Case Number": "PTR17301034",
      "Case Title": "***TRANSFERRED TO ALAMEDA COUNTY***IN THE MATTER OF THE THE MAYA VIZZI SETTLEMENT TRUST",
      "Court Date": "2017-10-16 09:00 AM",
      "Examiner": "TRUDY J. VERZOSA",
      "Calendar Matter": "ADDED TO CALENDAR FOR Status On Filing Of A Petition For Change Of Venue",
      "Rulings": "Off calendar",
      "Judge": "Trudy J. Verzosa"
    },
    {
      "Case Number": "PTR17301085",
      "Case Title": "IN THE MATTER OF THE BROWN FAMILY DTD AUGUST 13, 2010 TRUST",
      "Court Date": "2017-10-16 09:00 AM",
      "Examiner": "HELEN TROWBRIDGE",
      "Calendar Matter": "Petition For Order Approving Modification Of Trust",
      "Rulings": "Hearing. Appearance required.",
      "Judge": "Helen Trowbridge"
    },
    {
      "Case Number": "PTR17301111",
      "Case Title": "IN THE MATTER OF THE BRUCE G. COHEN REVOCABLE LIVING TRUST",
      "Court Date": "2017-10-16 09:00 AM",
      "Examiner": "TRUDY J. VERZOSA",
      "Calendar Matter": "Petition To Determine Title And Transfer Property To Trust",
      "Rulings": "Continued to 10/23/17 - Appearance will be required on that date.",
      "Judge": "Trudy J. Verzosa"
    },
    {
      "Case Number": "PES17301141",
      "Case Title": "THE ESTATE OF GREGORY JON FRAUNFELDER",
      "Court Date": "2017-10-16 09:00 AM",
      "Examiner": "SANDRA HILTON",
      "Calendar Matter": "PETITION FOR PROBATE OF WILL AND FOR LETTERS TESTAMENTARY",
      "Rulings": "hearing. appearance required as petition seeks admission to probate of a lost will.",
      "Judge": "Sandra Hilton"
    },
    {
      "Case Number": "PES17301146",
      "Case Title": "THE ESTATE OF ROBERT H LEE SR",
      "Court Date": "2017-10-16 09:00 AM",
      "Examiner": "HELEN TROWBRIDGE",
      "Calendar Matter": "PETITION FOR PROBATE OF WILL AND FOR LETTERS TESTAMENTARY",
      "Rulings": "Continued to 11/13/17. No response to Examiner's Notes.",
      "Judge": "Helen Trowbridge"
    },
    {
      "Case Number": "PTR17301172",
      "Case Title": "IN THE MATTER OF THE 1991 LILY JEAN LOW LIVING TRUST AS AMENDED TRUST",
      "Court Date": "2017-10-16 09:00 AM",
      "Examiner": "SANDRA HILTON",
      "Calendar Matter": "Petition For Appointment Of Trustee",
      "Rulings": "continued to november 6, 2017. no file stamped copy of the pleading and no proposed order delivered to the examiner as required by Local Rule. New deadline for providing both documents to the examiner in Room 202 is Wednesday, November 1, 2017. NOTE-->faxed or emailed copies are NOT accepted.",
      "Judge": "Sandra Hilton"
    },
    {
      "Case Number": "PES17301177",
      "Case Title": "THE ESTATE OF PETER R DALLMAN",
      "Court Date": "2017-10-16 09:00 AM",
      "Examiner": "TIMOTHY KNEIS",
      "Calendar Matter": "PETITION FOR SPOUSAL PROPERTY",
      "Rulings": "Hearing.",
      "Judge": "Timothy Kneis"
    },
    {
      "Case Number": "PES17301233",
      "Case Title": "THE ESTATE OF BRUCE V.A. BONACKER",
      "Court Date": "2017-10-16 09:00 AM",
      "Examiner": "HELEN TROWBRIDGE",
      "Calendar Matter": "PETITION FOR PROBATE OF WILL AND FOR LETTERS TESTAMENTARY",
      "Rulings": "Grant without hearing. Status of closing set for 4/17/19.",
      "Judge": "Helen Trowbridge"
    },
    {
      "Case Number": "PES17301236",
      "Case Title": "THE ESTATE OF HANS HENRY HELLEY JR",
      "Court Date": "2017-10-16 09:00 AM",
      "Examiner": "TRUDY J. VERZOSA",
      "Calendar Matter": "PETITION FOR LETTERS OF ADMINISTRATION",
      "Rulings": "Continued to 11/6/17 - Notes emailed 10/11/17",
      "Judge": "Trudy J. Verzosa"
    },
    {
      "Case Number": "PES17301254",
      "Case Title": "IN RE: FARHAD AKRAMI",
      "Court Date": "2017-10-16 09:00 AM",
      "Examiner": "SANDRA HILTON",
      "Calendar Matter": "PETITION TO ESTABLISH FACT OF BIRTH",
      "Rulings": "hearing. appearance required.",
      "Judge": "Sandra Hilton"
    },
    {
      "Case Number": "PES17301297",
      "Case Title": "IN RE: NASIAH DIVINE CARPENTER",
      "Court Date": "2017-10-16 09:00 AM",
      "Examiner": "SANDRA HILTON",
      "Calendar Matter": "PETITION TO ESTABLISH FACT OF BIRTH",
      "Rulings": "continued to october 30, 2017 at petitioner's request to allow time to file supporting documentation.",
      "Judge": "Sandra Hilton"
    }
  ],
  "_date": "2017-10-16"
}