{
  "department": "204",
  "scraped_at": "2026-05-03T16:36:32.459Z",
  "source_url": "https://webapps.sftc.org/tr/tr.dll?RulingID=7&SessionID=5A39A5C42348EC74FED98239B0B6F3A6B715AD2E",
  "reported_total": 73,
  "rulings": [
    {
      "Case Number": "PES94263644",
      "Case Title": "EST. OF VELERSTEAN BEATRICE BARFIELD",
      "Court Date": "2021-03-08 09:00 AM",
      "Examiner": "SEAN BANG",
      "Calendar Matter": "PROBATE ACCOUNTING STATUS PETITION",
      "Rulings": "Grant without hearing",
      "Judge": "Sean Bang"
    },
    {
      "Case Number": "PCN06288391",
      "Case Title": "CONSERVATORSHIP OF ALICE KAHANA",
      "Court Date": "2021-03-08 09:00 AM",
      "Examiner": "SANDRA HILTON",
      "Calendar Matter": "ADDED TO CALENDAR FOR Status Of Petition To Terminate Conservatorship And On Waiver Of Accounting Due To The Death Of The Conservatee",
      "Rulings": "off calendar",
      "Judge": "Sandra Hilton"
    },
    {
      "Case Number": "PES09293019",
      "Case Title": "IN RE: STANLEY CHONG KWONG",
      "Court Date": "2021-03-08 09:00 AM",
      "Examiner": "BRANDON SLYKHOUS",
      "Calendar Matter": "ADDED TO CALENDAR FOR Status Of The Order Regarding The Stipulation To Extend The Five Year Statute",
      "Rulings": "OFF CALENDAR. Parties need to follow the local rules for ex parte procedures. [LRSF 14.11 B.]",
      "Judge": "Brandon Slykhous"
    },
    {
      "Case Number": "PTR10293450",
      "Case Title": "IN RE: THE GWENN M. BENEDICT TRUST ESTABLISHED BY SUBSTITUTED JUDGMENT ON APRIL 6, 2001",
      "Court Date": "2021-03-08 09:00 AM",
      "Examiner": "EDWARD MIYAUCHI",
      "Calendar Matter": "FUTURE ACCOUNTING",
      "Rulings": "OFF CALENDAR",
      "Judge": "Edward Miyauchi"
    },
    {
      "Case Number": "PGN10293766",
      "Case Title": "GUARDIANSHIP OF AMIR SIMBULAN NASSER",
      "Court Date": "2021-03-08 09:00 AM",
      "Examiner": "SANDRA HILTON",
      "Calendar Matter": "ADDED TO CALENDAR FOR Status On Filing A Petition To Appoint A Successor Guardian",
      "Rulings": "continued to 4/5/21. petition to appoint successor filed, set for 3/16/21.",
      "Judge": "Sandra Hilton"
    },
    {
      "Case Number": "PCN11294454",
      "Case Title": "CONSERVATORSHIP OF ELINA YERAMIAN",
      "Court Date": "2021-03-08 09:00 AM",
      "Examiner": "SEAN BANG",
      "Calendar Matter": "ACCOUNTING PETITION RE: Accounting #5, Report, Fees",
      "Rulings": "Continued to 3/29/21. Examiner's Notes will be sent.",
      "Judge": "Sean Bang"
    },
    {
      "Case Number": "PES11294559",
      "Case Title": "THE ESTATE OF YAT MAN SIK",
      "Court Date": "2021-03-08 09:00 AM",
      "Examiner": "SEAN BANG",
      "Calendar Matter": "ACCOUNTING PETITION RE: Accounting #5, Report, Fees",
      "Rulings": "Grant without hearing",
      "Judge": "Sean Bang"
    },
    {
      "Case Number": "PGN12295418",
      "Case Title": "GUARDIANSHIP OF MIKAYLA PERIEFF et al",
      "Court Date": "2021-03-08 09:00 AM",
      "Examiner": "EDWARD MIYAUCHI",
      "Calendar Matter": "ADDED TO CALENDAR FOR Status On Filing Final Account Or Waiver Of Final Account",
      "Rulings": "OFF CALENDAR",
      "Judge": "Edward Miyauchi"
    },
    {
      "Case Number": "PCN12295627",
      "Case Title": "CONSERVATORSHIP OF ALEX SANDLER",
      "Court Date": "2021-03-08 09:00 AM",
      "Examiner": "SEAN BANG",
      "Calendar Matter": "ACCOUNTING PETITION RE: Accounting #5, Report, Fees",
      "Rulings": "Grant without hearing",
      "Judge": "Sean Bang"
    },
    {
      "Case Number": "PCN13297064",
      "Case Title": "CONSERVATORSHIP OF MODRA SPROGIS",
      "Court Date": "2021-03-08 09:00 AM",
      "Examiner": "BRANDON SLYKHOUS",
      "Calendar Matter": "FUTURE ACCOUNTING",
      "Rulings": "Hearing appearance required. Remote appearance by video or telephone should be made whenever possible. Please review the 9th amended general order for more information. To appear by Zoom, go to Zoom.com and click Join Meeting, and use the ID and password below. Meeting ID: 875 8017 7925 Password: 722809 To appear by telephone through Zoom, call 1-669-900-6833 and follow the prompts, using the meeting ID and password above. Parties appearing should check in for the hearing using their full name. Issue: the conservator has failed to account.",
      "Judge": "Brandon Slykhous"
    },
    {
      "Case Number": "PCN13297104",
      "Case Title": "CONSERVATORSHIP OF WILLIAM WADE GREENE",
      "Court Date": "2021-03-08 09:00 AM",
      "Examiner": "HELEN TROWBRIDGE",
      "Calendar Matter": "FUTURE ACCOUNTING",
      "Rulings": "Hearing. Appearance required. No hearing notes will be sent, as Counsel is already aware of this continued status hearing. Due to the COVID-19 emergency, counsel and parties must, whenever possible, appear remotely through Zoom or CourtCall. Please review the 9th amended general order on the court's website for information on appearing remotely. For Zoom appearance: meeting ID is 875 8017 7925 and password is 722809. For audio-only telephone appearance via Zoom, call 1-669-900-6833 and follow the prompts, using the meeting ID and password above. PARTIES APPEARING SHOULD CHECK IN FOR THE HEARING USING THEIR FULL NAME.",
      "Judge": "Helen Trowbridge"
    },
    {
      "Case Number": "PTR14297410",
      "Case Title": "IN RE: ELINA YERAMIAN 2013 LIVING TRUST",
      "Court Date": "2021-03-08 09:00 AM",
      "Examiner": "SEAN BANG",
      "Calendar Matter": "ACCOUNTING PETITION RE: Accounting #4, Report, Fees",
      "Rulings": "Continued to 3/29/21. Examiner's Notes will be sent.",
      "Judge": "Sean Bang"
    },
    {
      "Case Number": "PES15298483",
      "Case Title": "THE ESTATE OF GUADALUPE OCHOA",
      "Court Date": "2021-03-08 09:00 AM",
      "Examiner": "HELEN TROWBRIDGE",
      "Calendar Matter": "ACCOUNTING PETITION RE: Report, Fees, Final Distribution",
      "Rulings": "Continued to 4/5/21 at Counsel's request. (No earlier continuance date available.)",
      "Judge": "Helen Trowbridge"
    },
    {
      "Case Number": "PES15298784",
      "Case Title": "THE ESTATE OF HARVEY BARTNOF",
      "Court Date": "2021-03-08 09:00 AM",
      "Examiner": "SANDRA HILTON",
      "Calendar Matter": "Petition To Approve Forensic Account Of Administrator Wwa For Period From April 12 2015 To November 27 2019",
      "Rulings": "continued to 3/22/21 at counsel's request.",
      "Judge": "Sandra Hilton"
    },
    {
      "Case Number": "PCN15299200",
      "Case Title": "CONSERVATORSHIP OF ROBERT S. BULLEN",
      "Court Date": "2021-03-08 09:00 AM",
      "Examiner": "BRANDON SLYKHOUS",
      "Calendar Matter": "FUTURE ACCOUNTING",
      "Rulings": "OFF CALENDAR",
      "Judge": "Brandon Slykhous"
    },
    {
      "Case Number": "PCN16299930",
      "Case Title": "CONSERVATORSHIP OF ERNESTOR ROJAS",
      "Court Date": "2021-03-08 09:00 AM",
      "Examiner": "BRANDON SLYKHOUS",
      "Calendar Matter": "ADDED TO CALENDAR FOR Status Of Petition To Terminate Conservatorship And Of The Final Accounting Due To The Death Of The Conservatee",
      "Rulings": "Hearing appearance required. Remote appearance by video or telephone should be made whenever possible. Please review the 9th amended general order for more information. To appear by Zoom, go to Zoom.com and click Join Meeting, and use the ID and password below. Meeting ID: 875 8017 7925 Password: 722809 To appear by telephone through Zoom, call 1-669-900-6833 and follow the prompts, using the meeting ID and password above. Parties appearing should check in for the hearing using their full name. ISSUES: 1) A petition to terminate conservatorship and of the final account due to the death of the conservatee has not been filed.",
      "Judge": "Brandon Slykhous"
    },
    {
      "Case Number": "PES16300199",
      "Case Title": "THE ESTATE OF JEANNE D. O'DONNELL",
      "Court Date": "2021-03-08 09:00 AM",
      "Examiner": "EDWARD MIYAUCHI",
      "Calendar Matter": "ACCOUNTING PETITION RE: Accounting #1, Report, Fees, Final Distribution",
      "Rulings": "Continued to 03/29/2021. 1) Paragraph 5 of the petition does not state whether notice to any entity was required under Probate Code section 9201. 2) The statutory fee base set forth in paragraph 21 of the petition must be reduced by the loss. 3) Was court approval obtained for the two payments reported as \"PA Legal Fees\" on Schedule C? Did the petitioner retain this attorney? 4) Some disbursements reported on Schedule C were made before letters were issued. Are the payment dates accurate? 5) As to the funeral expenses reported on Schedule C, were creditor claims filed? The disbursement on 11/21/19 appears to be a claim by the petitioner, but no court approval has been obtained. Probate Code sections 9252 and 9000(a)(3). 6) The disbursements to the petitioner's attorneys reported on Schedule C as \"Costs\" must be itemized. 7) Please provide copies of receipts for the court costs of $76.50 on 2/21/17 & $88.50 on 10/3/19. 8) Schedule C mentions the decedent's \"SNT\". Was the decedent receiving Medi-Cal benefits? 9) The declaration re retention of bank statements must state that the attorney retains the \"original\" statements. 10) The proposed order must comply with CRC 7.650(b) re distribution to the supplemental needs trust.",
      "Judge": "Edward Miyauchi"
    },
    {
      "Case Number": "PCN16300209",
      "Case Title": "CONSERVATORSHIP OF DONALD J REBELLO",
      "Court Date": "2021-03-08 09:00 AM",
      "Examiner": "BRANDON SLYKHOUS",
      "Calendar Matter": "ACCOUNTING PETITION RE: Report, Fees",
      "Rulings": "Continued to 4/12/2021 at request of attorney.",
      "Judge": "Brandon Slykhous"
    },
    {
      "Case Number": "PES16300366",
      "Case Title": "THE ESTATE OF FLORENCE CHANG",
      "Court Date": "2021-03-08 09:00 AM",
      "Examiner": "EDWARD MIYAUCHI",
      "Calendar Matter": "ACCOUNTING PETITION RE: Final Distribution",
      "Rulings": "Continued to 03/29/2021. A courtesy copy of the supplement has not been received.",
      "Judge": "Edward Miyauchi"
    },
    {
      "Case Number": "PES16300421",
      "Case Title": "THE ESTATE OF RICHARD GORDON SELF",
      "Court Date": "2021-03-08 09:00 AM",
      "Examiner": "HELEN TROWBRIDGE",
      "Calendar Matter": "ADDED TO CALENDAR FOR Status On Close Of Estate",
      "Rulings": "Hearing. Appearance required. No hearing notes will be sent, as Counsel is already aware of this continued status hearing. No petition, either for final distribution or for additional time to administer the estate, has been filed yet nearly 11 months after one was to have been filed. Due to the COVID-19 emergency, counsel and parties must, whenever possible, appear remotely through Zoom or CourtCall. Please review the 9th amended general order on the court's website for information on appearing remotely. For Zoom appearance: meeting ID is 875 8017 7925 and password is 722809. For audio-only telephone appearance via Zoom, call 1-669-900-6833 and follow the prompts, using the meeting ID and password above. PARTIES APPEARING SHOULD CHECK IN FOR THE HEARING USING THEIR FULL NAME.",
      "Judge": "Helen Trowbridge"
    },
    {
      "Case Number": "PES17301065",
      "Case Title": "THE ESTATE OF WILLIAM L. HOLTON",
      "Court Date": "2021-03-08 09:00 AM",
      "Examiner": "HELEN TROWBRIDGE",
      "Calendar Matter": "ACCOUNTING PETITION RE: Accounting #2, Report, Fees, Final Distribution",
      "Rulings": "Continued to 4/12/21. Still no certified copy of Letters of Guardianship from New York. (No earlier availability.)",
      "Judge": "Helen Trowbridge"
    },
    {
      "Case Number": "PES18301506",
      "Case Title": "THE ESTATE OF RICHARD ELTON MORRI",
      "Court Date": "2021-03-08 09:00 AM",
      "Examiner": "SANDRA HILTON",
      "Calendar Matter": "Petition To Determine Entitlement To Estate Distribution [Probate Code 11700]",
      "Rulings": "continued to 3/15/21 for calendar management and to allow time for a pending objection to be filed and a copy delivered to the examiner.",
      "Judge": "Sandra Hilton"
    },
    {
      "Case Number": "PES18301666",
      "Case Title": "THE ESTATE OF AMY J. REECE",
      "Court Date": "2021-03-08 09:00 AM",
      "Examiner": "EDWARD MIYAUCHI",
      "Calendar Matter": "ACCOUNTING PETITION RE: Accounting #1, Report, Fees, Final Distribution",
      "Rulings": "Continued to 03/15/2021 to be heard by Judge Moody. Updated notes were e-mailed to both counsel on 03/01/2021.",
      "Judge": "Edward Miyauchi"
    },
    {
      "Case Number": "PES18301770",
      "Case Title": "THE ESTATE OF MEIR O'BRIEN",
      "Court Date": "2021-03-08 09:00 AM",
      "Examiner": "BRANDON SLYKHOUS",
      "Calendar Matter": "ACCOUNTING PETITION RE: Accounting #1, Report, Fees, Final Distribution",
      "Rulings": "Grant without hearing",
      "Judge": "Brandon Slykhous"
    },
    {
      "Case Number": "PGN18301793",
      "Case Title": "GUARDIANSHIP OF KANE JACKSON LEUNG ET AL",
      "Court Date": "2021-03-08 09:00 AM",
      "Examiner": "BRANDON SLYKHOUS",
      "Calendar Matter": "ORDER OF STATUS HEARING",
      "Rulings": "Hearing appearance required. Remote appearance by video or telephone should be made whenever possible. Please review the 9th amended general order for more information. To appear by Zoom, go to Zoom.com and click Join Meeting, and use the ID and password below. Meeting ID: 875 8017 7925 Password: 722809 To appear by telephone through Zoom, call 1-669-900-6833 and follow the prompts, using the meeting ID and password above. Parties appearing should check in for the hearing using their full name. ISSUES (may be addressed at hearing): 1) No Final I&A filed. Court to determine how to proceed. 2) No receipt filed showing funds placed into a blocked account.",
      "Judge": "Brandon Slykhous"
    },
    {
      "Case Number": "PGN18301793",
      "Case Title": "GUARDIANSHIP OF KANE JACKSON LEUNG ET AL",
      "Court Date": "2021-03-08 09:00 AM",
      "Examiner": "BRANDON SLYKHOUS",
      "Calendar Matter": "ADDED TO CALENDAR FOR Status On Filing Of The Receipt For The Blocked Account",
      "Rulings": "Hearing appearance required. Remote appearance by video or telephone should be made whenever possible. Please review the 9th amended general order for more information. To appear by Zoom, go to Zoom.com and click Join Meeting, and use the ID and password below. Meeting ID: 875 8017 7925 Password: 722809 To appear by telephone through Zoom, call 1-669-900-6833 and follow the prompts, using the meeting ID and password above. Parties appearing should check in for the hearing using their full name. ISSUES (may be addressed at hearing): 1) No Final I&A filed. Court to determine how to proceed. 2) No receipt filed showing funds placed into a blocked account.",
      "Judge": "Brandon Slykhous"
    },
    {
      "Case Number": "PGN18301793",
      "Case Title": "GUARDIANSHIP OF KANE JACKSON LEUNG ET AL",
      "Court Date": "2021-03-08 09:00 AM",
      "Examiner": "BRANDON SLYKHOUS",
      "Calendar Matter": "FILING OF INVENTORY",
      "Rulings": "Hearing appearance required. Remote appearance by video or telephone should be made whenever possible. Please review the 9th amended general order for more information. To appear by Zoom, go to Zoom.com and click Join Meeting, and use the ID and password below. Meeting ID: 875 8017 7925 Password: 722809 To appear by telephone through Zoom, call 1-669-900-6833 and follow the prompts, using the meeting ID and password above. Parties appearing should check in for the hearing using their full name. ISSUES (may be addressed at hearing): 1) No Final I&A filed. Court to determine how to proceed. 2) No receipt filed showing funds placed into a blocked account.",
      "Judge": "Brandon Slykhous"
    },
    {
      "Case Number": "PES18302221",
      "Case Title": "THE ESTATE OF RICHARD ATTILIO DEMARTINI",
      "Court Date": "2021-03-08 09:00 AM",
      "Examiner": "EDWARD MIYAUCHI",
      "Calendar Matter": "PROBATE ACCOUNTING STATUS PETITION",
      "Rulings": "OFF CALENDAR (petition for final distribution filed and set for hearing).",
      "Judge": "Edward Miyauchi"
    },
    {
      "Case Number": "PES18302226",
      "Case Title": "THE ESTATE OF LINNA CHINN YI WANG",
      "Court Date": "2021-03-08 09:00 AM",
      "Examiner": "BRANDON SLYKHOUS",
      "Calendar Matter": "PROBATE ACCOUNTING STATUS PETITION",
      "Rulings": "Continued to 4/5/2021. 1) Petitioner has not filed DE-120 showing proper notice of the status petition.",
      "Judge": "Brandon Slykhous"
    },
    {
      "Case Number": "PES18302326",
      "Case Title": "THE ESTATE OF LILLAS B. MCENTEE",
      "Court Date": "2021-03-08 09:00 AM",
      "Examiner": "HELEN TROWBRIDGE",
      "Calendar Matter": "ACCOUNTING PETITION RE: Report, Fees, Final Distribution",
      "Rulings": "Grant without hearing",
      "Judge": "Helen Trowbridge"
    },
    {
      "Case Number": "PES19302490",
      "Case Title": "THE ESTATE OF ADRIAN M. TYLER",
      "Court Date": "2021-03-08 09:00 AM",
      "Examiner": "HELEN TROWBRIDGE",
      "Calendar Matter": "ACCOUNTING PETITION RE: Accounting, Report, Fees, Final Distribution",
      "Rulings": "Continued to 4/12/21. No courtesy copies. No proposed order. No proof of service. Courtesy copies and a proposed order must be received by the assigned Examiner by no later than 4/2/21.",
      "Judge": "Helen Trowbridge"
    },
    {
      "Case Number": "PTR19302545",
      "Case Title": "IN THE MATTER OF THE THE LAMARCUS GREGORY SPECIAL NEEDS TRUST",
      "Court Date": "2021-03-08 09:00 AM",
      "Examiner": "HELEN TROWBRIDGE",
      "Calendar Matter": "ACCOUNTING PETITION RE: Accounting #1, Report",
      "Rulings": "Hearing. Appearance required. Due to the COVID-19 emergency, counsel and parties must, whenever possible, appear remotely through Zoom or CourtCall. Please review the 9th amended general order on the court's website for information on appearing remotely. For Zoom appearance: meeting ID is 875 8017 7925 and password is 722809. For audio-only telephone appearance via Zoom, call 1-669-900-6833 and follow the prompts, using the meeting ID and password above. PARTIES APPEARING SHOULD CHECK IN FOR THE HEARING USING THEIR FULL NAME.",
      "Judge": "Helen Trowbridge"
    },
    {
      "Case Number": "PTR19302561",
      "Case Title": "IN THE MATTER OF THE JAMES C. GRIMES REVOCABLE INTERVIVOS TRUST",
      "Court Date": "2021-03-08 09:00 AM",
      "Examiner": "HELEN TROWBRIDGE",
      "Calendar Matter": "ACCOUNTING PETITION RE: Accounting #2, Fees",
      "Rulings": "Continued to 3/29/21. A copy of the seller's closing statement was not filed to verify the costs of sale. Some other disbursements are also missing the identity of the payee. What is meant by \"Willie-non profit\"? The bank statement does not encompass the ending date of the accounting period. Courtesy copies of any papers filed to address these issues must be received by the assigned Examiner by no later than 3/19/21.",
      "Judge": "Helen Trowbridge"
    },
    {
      "Case Number": "PTR19302604",
      "Case Title": "IN THE MATTER OF THE SHAPIRO FAMILY TRUST",
      "Court Date": "2021-03-08 09:00 AM",
      "Examiner": "SEAN BANG",
      "Calendar Matter": "ACCOUNTING PETITION RE: Accounting #1, Report, Fees",
      "Rulings": "Continued to 4/5/21. The issues raised in prior tentative ruling have not yet been addressed, which must be addressed prior to a full review of the petition: 1) I&A must be filed and Notice of Filing I&A given. 2) Maxwell Shapiro has not been given proper notice. The notice filed on 1/26/21 shows that he was given less than 30 day notice. 3) Request for reduction of bond was not included in the prayer of the petition. Filed stamped copy of any required pleading must be provided 2 weeks prior to Room 202.",
      "Judge": "Sean Bang"
    },
    {
      "Case Number": "PES19302656",
      "Case Title": "THE ESTATE OF GERARD CONCANNON",
      "Court Date": "2021-03-08 09:00 AM",
      "Examiner": "EDWARD MIYAUCHI",
      "Calendar Matter": "ACCOUNTING PETITION RE: Accounting, Report, Fees, Final Distribution",
      "Rulings": "Continued to 03/15/2021 to be heard by Judge Moody.",
      "Judge": "Edward Miyauchi"
    },
    {
      "Case Number": "PES19302805",
      "Case Title": "THE ESTATE OF PAUL DUNCAN QUICK",
      "Court Date": "2021-03-08 09:00 AM",
      "Examiner": "SANDRA HILTON",
      "Calendar Matter": "ADDED TO CALENDAR FOR Status Of Closing The Estate",
      "Rulings": "hearing. appearance required for counsel to explain why neither a petition for final distribution nor a petition to approve status of administration has been filed. Due to the COVID-19 emergency, counsel and parties must, whenever possible, appear remotely through Zoom or CourtCall. Please review the 9th amended general order on the court’s website for information on appearing remotely. For Zoom appearance: meeting ID is 875 8017 7925 and password is 722809. For audio-only telephone appearance via Zoom, call 1-669-900-6833 and follow the prompts, using the meeting ID and password above. PARTIES APPEARING SHOULD CHECK IN FOR THE HEARING USING THEIR FULL NAME.",
      "Judge": "Sandra Hilton"
    },
    {
      "Case Number": "PGN19302811",
      "Case Title": "GUARDIANSHIP OF JACOB DILLON JOHNSON",
      "Court Date": "2021-03-08 09:00 AM",
      "Examiner": "SANDRA HILTON",
      "Calendar Matter": "ADDED TO CALENDAR FOR Status On The Filing Of A Receipt For Funds Released From The Blocked Account",
      "Rulings": "continued to 3/22/21 to allow time for counsel to file a receipt for distribution of the funds.",
      "Judge": "Sandra Hilton"
    },
    {
      "Case Number": "PES19302844",
      "Case Title": "THE ESTATE OF CARLOS ENRIQUE DELGADILLO",
      "Court Date": "2021-03-08 09:00 AM",
      "Examiner": "HELEN TROWBRIDGE",
      "Calendar Matter": "ACCOUNTING PETITION RE: Report, Fees, Final Distribution",
      "Rulings": "Grant without hearing, although a supplement to a petition should simply stand on its own and not refer to issues raised by the Court or posted in tentative rulings. (Except for exhibits, each paper filed with the court must bear a footer in the bottom margin of each page, placed below the page number and divided from the rest of the document page by a printed line. [CRC 2.110(a).])",
      "Judge": "Helen Trowbridge"
    },
    {
      "Case Number": "PCN19302868",
      "Case Title": "CONSERVATORSHIP OF YOOK JUNG LEW",
      "Court Date": "2021-03-08 09:00 AM",
      "Examiner": "SEAN BANG",
      "Calendar Matter": "FILING OF FIRST ACCOUNT",
      "Rulings": "Continued to 4/26/21.",
      "Judge": "Sean Bang"
    },
    {
      "Case Number": "PCN19302868",
      "Case Title": "CONSERVATORSHIP OF YOOK JUNG LEW",
      "Court Date": "2021-03-08 09:00 AM",
      "Examiner": "SEAN BANG",
      "Calendar Matter": "FILING OF STATUS REPORT",
      "Rulings": "off calendar",
      "Judge": "Sean Bang"
    },
    {
      "Case Number": "PES19302871",
      "Case Title": "THE ESTATE OF DOUGLAS P WILLIAMS",
      "Court Date": "2021-03-08 09:00 AM",
      "Examiner": "EDWARD MIYAUCHI",
      "Calendar Matter": "PROBATE ACCOUNTING STATUS PETITION",
      "Rulings": "OFF CALENDAR (petition for final distribution filed and set for hearing).",
      "Judge": "Edward Miyauchi"
    },
    {
      "Case Number": "PES19302876",
      "Case Title": "THE ESTATE OF OLDEN HAROLD WILLIAMS",
      "Court Date": "2021-03-08 09:00 AM",
      "Examiner": "SEAN BANG",
      "Calendar Matter": "PROBATE ACCOUNTING STATUS PETITION",
      "Rulings": "Continued to 3/29/21. Examiner's Notes emailed on 2/25/21.",
      "Judge": "Sean Bang"
    },
    {
      "Case Number": "PES19302933",
      "Case Title": "THE ESTATE OF PAUL LEWIN",
      "Court Date": "2021-03-08 09:00 AM",
      "Examiner": "SEAN BANG",
      "Calendar Matter": "ADDED TO CALENDAR FOR Status Of Closing The Estate",
      "Rulings": "off calendar",
      "Judge": "Sean Bang"
    },
    {
      "Case Number": "PTR19303005",
      "Case Title": "IN THE MATTER OF THE MANUEL AND LUCY ABEYTA FAMILY TRUST",
      "Court Date": "2021-03-08 09:00 AM",
      "Examiner": "HELEN TROWBRIDGE",
      "Calendar Matter": "Petition For Appointment Of Shirley Basch As Successor Trustee",
      "Rulings": "Hearing. Appearance required. No hearing notes will be sent. The Court to determine the status of the real property sale closing and the deposit of funds into a blocked account. Pursuant to the relief sought in the amended petition, there does not appear to be any need for continuing supervision of the trust. Due to the COVID-19 emergency, counsel and parties must, whenever possible, appear remotely through Zoom or CourtCall. Please review the 9th amended general order on the court’s website for information on appearing remotely. For Zoom appearance: meeting ID is 875 8017 7925 and password is 722809. For audio-only telephone appearance via Zoom, call 1-669-900-6833 and follow the prompts, using the meeting ID and password above. PARTIES APPEARING SHOULD CHECK IN FOR THE HEARING USING THEIR FULL NAME.",
      "Judge": "Helen Trowbridge"
    },
    {
      "Case Number": "PES19303022",
      "Case Title": "THE ESTATE OF MICHIKO KAWATA",
      "Court Date": "2021-03-08 09:00 AM",
      "Examiner": "EDWARD MIYAUCHI",
      "Calendar Matter": "ACCOUNTING PETITION RE: Final Distribution",
      "Rulings": "Continued to 04/12/2021. Courtesy copies of the documents filed by the assignee of the predeceased spouse's children claiming to be heirs have not been received. A petition to determine those children's entitlement to distribution must be filed and adjudicated before the Court can proceed with this petition.",
      "Judge": "Edward Miyauchi"
    },
    {
      "Case Number": "PCN19303107",
      "Case Title": "CONSERVATORSHIP OF SEIGFRIED ANGELO LUNTAO LIM",
      "Court Date": "2021-03-08 09:00 AM",
      "Examiner": "HELEN TROWBRIDGE",
      "Calendar Matter": "FILING OF FIRST ACCOUNT",
      "Rulings": "Continued to 4/12/21. Attorney was notified on 3/2/21.",
      "Judge": "Helen Trowbridge"
    },
    {
      "Case Number": "PCN19303107",
      "Case Title": "CONSERVATORSHIP OF SEIGFRIED ANGELO LUNTAO LIM",
      "Court Date": "2021-03-08 09:00 AM",
      "Examiner": "HELEN TROWBRIDGE",
      "Calendar Matter": "FILING OF STATUS REPORT",
      "Rulings": "Continued to 4/12/21. Attorney was notified on 3/2/21.",
      "Judge": "Helen Trowbridge"
    },
    {
      "Case Number": "PES19303181",
      "Case Title": "THE ESTATE OF SALVATORE G. CRESCI",
      "Court Date": "2021-03-08 09:00 AM",
      "Examiner": "SEAN BANG",
      "Calendar Matter": "ACCOUNTING PETITION RE: Report, Fees, Final Distribution",
      "Rulings": "Grant without hearing",
      "Judge": "Sean Bang"
    },
    {
      "Case Number": "PCN19303272",
      "Case Title": "CONSERVATORSHIP OF GEORGIA E HUNT",
      "Court Date": "2021-03-08 09:00 AM",
      "Examiner": "BRANDON SLYKHOUS",
      "Calendar Matter": "ADDED TO CALENDAR FOR Status Of Petition To Terminate Conservatorship And Of The Final Accounting Due To The Death Of The Conservatee",
      "Rulings": "Hearing appearance required. Remote appearance by video or telephone should be made whenever possible. Please review the 9th amended general order for more information. To appear by Zoom, go to Zoom.com and click Join Meeting, and use the ID and password below. Meeting ID: 875 8017 7925 Password: 722809 To appear by telephone through Zoom, call 1-669-900-6833 and follow the prompts, using the meeting ID and password above. Parties appearing should check in for the hearing using their full name. ISSUES: A petition to terminate this conservatorship including final report has not been filed.",
      "Judge": "Brandon Slykhous"
    },
    {
      "Case Number": "PES19303321",
      "Case Title": "THE ESTATE OF KATHERINE LYNDS",
      "Court Date": "2021-03-08 09:00 AM",
      "Examiner": "EDWARD MIYAUCHI",
      "Calendar Matter": "ADDED TO CALENDAR FOR Status On Close Of Estate",
      "Rulings": "Hearing. Appearance required. Issues may include (but not limited to): No petition for final distribution or petition for approval of report of status of administration has been filed. PARTIES APPEARING SHOULD CHECK IN FOR THE HEARING WITH THEIR FULL NAME. Counsel and parties must, whenever possible, appear remotely through Zoom or CourtCall. For a video appearance, go to zoom.us, click \"join a meeting\" and input meeting ID 875 8017 7925 and password 722809. For an audio-only appearance through Zoom, call 1-669-900-6833 and key in meeting ID \"875 8017 7925#\", then participant ID \"0#\", then password \"722809#\". (Toll rates may apply).) The Court prefers that counsel and parties appear by video and that they input their first and last name into the \"Your Name\" dialogue box. Counsel and parties may appear by audio-only telephone through CourtCall by calling 1-888-882-6878. Please review the Court's 9th Amended General Order which took effect on 02/10/2021 for more information.",
      "Judge": "Edward Miyauchi"
    },
    {
      "Case Number": "PTR19303401",
      "Case Title": "IN RE: LAURENCE B. KNOWLES",
      "Court Date": "2021-03-08 09:00 AM",
      "Examiner": "BRANDON SLYKHOUS",
      "Calendar Matter": "ACCOUNTING PETITION RE: Accounting #1, Report, Fees, First Accounting of Trustee",
      "Rulings": "Continued to 4/12/2021 at request of counsel. Endorsed-filed single sided courtesy copies are required for any papers filed with the court and must be received by Examiner in room 202 at the Superior Court. Examiners will not review any document until after it has been filed and a courtesy copy has been received. [LRSF 2.7, 14.7]. Petitioner must submit a hard copy of the proposed order to the Examiner in room 202 at least five (5) court days in advance of the scheduled hearing date, with the scheduled hearing date noted on the face sheet. [LRSF 14.7].",
      "Judge": "Brandon Slykhous"
    },
    {
      "Case Number": "PES20303486",
      "Case Title": "THE ESTATE OF LORENZO M EUGENIO",
      "Court Date": "2021-03-08 09:00 AM",
      "Examiner": "SANDRA HILTON",
      "Calendar Matter": "ACCOUNTING PETITION RE: Fees, Final Distribution",
      "Rulings": "grant without hearing.",
      "Judge": "Sandra Hilton"
    },
    {
      "Case Number": "PES20303558",
      "Case Title": "THE ESTATE OF NORMAN M. STEWART SR.",
      "Court Date": "2021-03-08 09:00 AM",
      "Examiner": "BRANDON SLYKHOUS",
      "Calendar Matter": "PETITION FOR PROBATE OF WILL AND FOR LETTERS TESTAMENTARY",
      "Rulings": "Continued to 4/14/2021 at request of counsel.",
      "Judge": "Brandon Slykhous"
    },
    {
      "Case Number": "PCN20303652",
      "Case Title": "CONSERVATORSHIP OF PAMELA ANNE TAYLOR",
      "Court Date": "2021-03-08 09:00 AM",
      "Examiner": "SEAN BANG",
      "Calendar Matter": "ADDED TO CALENDAR FOR Compliane Status Hearing",
      "Rulings": "Appearance required. Remote appearances should be made whenever possible. Please review the 9th amended general order. The following information pertains to appearances by Zoom: WHEN ENTERING \"YOUR NAME\" ON ZOOM, BOTH THE FIRST AND LAST NAME, AS WELL THE CASE NUMBER, MUST BE INCLUDED. Meeting ID: 875 8017 7925 Password: 722809 To appear by telephone through Zoom, call 1-669-900-6833, and follow the prompts, using the meeting ID and password above. Information regarding appearance by CourtCall can be found in the 9th amended general order.",
      "Judge": "Sean Bang"
    },
    {
      "Case Number": "PES20303702",
      "Case Title": "THE ESTATE OF MCNEAL VERNON WILLIAMS",
      "Court Date": "2021-03-08 09:00 AM",
      "Examiner": "HELEN TROWBRIDGE",
      "Calendar Matter": "REPORT OF SALE AND PETITION TO CONFIRM SALE OF REAL PROPERTY (62 Carr Street, San Francisco, Ca 94124)",
      "Rulings": "Hearing. Appearance required. Due to the COVID-19 emergency, counsel and parties must, whenever possible, appear remotely through Zoom or CourtCall. Please review the 9th amended general order on the court's website for information on appearing remotely. For Zoom appearance: meeting ID is 875 8017 7925 and password is 722809. For audio-only telephone appearance via Zoom, call 1-669-900-6833 and follow the prompts, using the meeting ID and password above. PARTIES APPEARING SHOULD CHECK IN FOR THE HEARING USING THEIR FULL NAME.",
      "Judge": "Helen Trowbridge"
    },
    {
      "Case Number": "PTR20303762",
      "Case Title": "IN THE MATTER OF THE NANCY EILEEN MARSDEN TRUST",
      "Court Date": "2021-03-08 09:00 AM",
      "Examiner": "EDWARD MIYAUCHI",
      "Calendar Matter": "Petition For Order Confirming Trust Assets",
      "Rulings": "Continued to 04/12/2021. The trustor's brother must be served in accordance with Probate Code section 851(a)(2).",
      "Judge": "Edward Miyauchi"
    },
    {
      "Case Number": "PTR20303765",
      "Case Title": "IN THE MATTER OF THE JOANNE ANDERSON REVOCABLE LIVING TRUST DATED FEBRUARY 25, 2020 TRUST",
      "Court Date": "2021-03-08 09:00 AM",
      "Examiner": "SANDRA HILTON",
      "Calendar Matter": "Petition For Order Confirming Successor Trustee And Trust Assets",
      "Rulings": "continued to 4/5/21. nothing filed in response to the examiner notes by the stated deadline of noon on 3/1/21. new filing deadline is noon on 3/29/21.",
      "Judge": "Sandra Hilton"
    },
    {
      "Case Number": "PES20303787",
      "Case Title": "THE ESTATE OF CATHRERINE ANNE PHILLIPS",
      "Court Date": "2021-03-08 09:00 AM",
      "Examiner": "SEAN BANG",
      "Calendar Matter": "ADDED TO CALENDAR FOR Status Hearing On Filing Proof Of Increased Bond",
      "Rulings": "Appearance required. Remote appearances should be made whenever possible. Please review the 9th amended general order. The following information pertains to appearances by Zoom: WHEN ENTERING \"YOUR NAME\" ON ZOOM, BOTH THE FIRST AND LAST NAME, AS WELL THE CASE NUMBER, MUST BE INCLUDED. Meeting ID: 875 8017 7925 Password: 722809 To appear by telephone through Zoom, call 1-669-900-6833, and follow the prompts, using the meeting ID and password above. Information regarding appearance by CourtCall can be found in the 9th amended general order.",
      "Judge": "Sean Bang"
    },
    {
      "Case Number": "PES20303798",
      "Case Title": "THE ESTATE OF GAYLE DOUB",
      "Court Date": "2021-03-08 09:00 AM",
      "Examiner": "EDWARD MIYAUCHI",
      "Calendar Matter": "PETITION FOR SPOUSAL PROPERTY",
      "Rulings": "Continued to 03/29/2021 per counsel's request (via e-mail on 03/03/2021).",
      "Judge": "Edward Miyauchi"
    },
    {
      "Case Number": "PES20303809",
      "Case Title": "THE ESTATE OF GEORGE WILLIAM MEACHAM JR.",
      "Court Date": "2021-03-08 09:00 AM",
      "Examiner": "HELEN TROWBRIDGE",
      "Calendar Matter": "ADDED TO CALENDAR FOR Status For Filing Inventory And Appraisal",
      "Rulings": "Continued to 4/26/21 at the request of one of the co-administrators and the attorney who will reportedly be substituting in as counsel for the co-administrators. Letters must be issued and the I&A must be filed no later than one week before 4/26/21.",
      "Judge": "Helen Trowbridge"
    },
    {
      "Case Number": "PTR20303912",
      "Case Title": "IN THE MATTER OF THE MIKHAIL M. VAYNBERG AND BEATRISA VAYNBERG LIVING TRUST",
      "Court Date": "2021-03-08 09:00 AM",
      "Examiner": "SANDRA HILTON",
      "Calendar Matter": "Petition To Remove Trustee, For Accounting, And For Breach Of Fiduciary Duty",
      "Rulings": "continued to 3/9/21 to be on calendar with competing petition. file stamped copy of petition (and opposition, if filed) must be delivered to the examiner in Room 202 by noon on 3/1/21.",
      "Judge": "Sandra Hilton"
    },
    {
      "Case Number": "PES20303949",
      "Case Title": "THE ESTATE OF THOMAS ELKING WESTERBERG",
      "Court Date": "2021-03-08 09:00 AM",
      "Examiner": "HELEN TROWBRIDGE",
      "Calendar Matter": "PETITION FOR PROBATE OF WILL AND FOR LETTERS TESTAMENTARY",
      "Rulings": "Hearing for the purpose of admitting the will dated May 10, 2019, although the pro per attorney petitioner did not set forth a physical address on his Duties and Liabilities. No appearance is required. Status of closing the estate will be set on 9/7/2022. A petition for final distribution or a report of status with a petition requesting additional time for estate administration must be filed at least one week before 9/7/2022. Appearance will be required on 9/7/2022 if no petition has been filed.",
      "Judge": "Helen Trowbridge"
    },
    {
      "Case Number": "PTR20303953",
      "Case Title": "IN THE MATTER OF THE KAREN GRANT 2016 LIVING TRUST",
      "Court Date": "2021-03-08 09:00 AM",
      "Examiner": "BRANDON SLYKHOUS",
      "Calendar Matter": "Petition For Order Determining Title To Real Property",
      "Rulings": "Continued to 4/13/2021. 1) DE-115 shows notice being mailed on 2/18/2021 for a 3/8/2021 hearing. 30 days notice required. [Probate Code 851] 2) The 2/22/2021 Supplemental Declaration of Jennifer Herrera alleges attached as exhibit A. There is no exhibit A attached.",
      "Judge": "Brandon Slykhous"
    },
    {
      "Case Number": "PTR20303964",
      "Case Title": "IN THE MATTER OF THE MAUREEN E. CROWE TRUST DATED JULY 16, 2016",
      "Court Date": "2021-03-08 09:00 AM",
      "Examiner": "HELEN TROWBRIDGE",
      "Calendar Matter": "Petition: For Removal, Appointment, Or Confirmation Of Trustee; For Breach Of Fiduciary Duty And Damages; To Compel Trust Accounting",
      "Rulings": "Continued to 4/26/21. No more hearing spots available on 3/8/21, a substitute judge will be on the bench on 3/8/21, and the petition should be heard after the motions. Additionally, the only ENDORSED FILED copy of the petitioners' pleadings that has been delivered to the Examiner so far is the petition filed on 10/16/20. [LRSF 14.7 B. and C.] The petition does not address how this is the proper venue; it appears that Gregory Crowe resides in Hawaii and James Feilders resides in Canada. It does not appear that all beneficiaries of the trust were listed in the petition. [CRC 7.902.] They did not receive notice. The proofs of service filed on 1/25/21 (no courtesy copies have been received by the Examiner so they were skimmed online) were not the proper form of Notice of Hearing for a petition filed pursuant to Probate Code Section 850.",
      "Judge": "Helen Trowbridge"
    },
    {
      "Case Number": "PTR20304055",
      "Case Title": "IN THE MATTER OF THE GLORIA M. EMBY REVOCABLE TRUST OF OCTOBER 9, 2000 TRUST",
      "Court Date": "2021-03-08 09:00 AM",
      "Examiner": "BRANDON SLYKHOUS",
      "Calendar Matter": "Petition For Approval Of Settlement And Trust Distribution Agreement To Modify Trust, And For Instructions To Trustee",
      "Rulings": "Continued to 4/5/2021. Issues: 1)Please file a memorandum of points and authorities in support of the stipulation for petition to be heard by a member of the California bar serving as a temporary judge in the probate court.",
      "Judge": "Brandon Slykhous"
    },
    {
      "Case Number": "PES20304090",
      "Case Title": "THE ESTATE OF ANTHONY CORBETT RICHMOND",
      "Court Date": "2021-03-08 09:00 AM",
      "Examiner": "BRANDON SLYKHOUS",
      "Calendar Matter": "PETITION FOR LETTERS OF ADMINISTRATION",
      "Rulings": "Grant without hearing. bond is fixed at $218,000.00. status on close of estate 9/7/2022.",
      "Judge": "Brandon Slykhous"
    },
    {
      "Case Number": "PES20304120",
      "Case Title": "THE ESTATE OF THOMAS L. MARK",
      "Court Date": "2021-03-08 09:00 AM",
      "Examiner": "SANDRA HILTON",
      "Calendar Matter": "PETITION FOR LETTERS OF ADMINISTRATION",
      "Rulings": "grant without hearing. close of estate set for 6/10/22.",
      "Judge": "Sandra Hilton"
    },
    {
      "Case Number": "PES21304134",
      "Case Title": "THE ESTATE OF PATRICIA VALUROSO SAILOR",
      "Court Date": "2021-03-08 09:00 AM",
      "Examiner": "EDWARD MIYAUCHI",
      "Calendar Matter": "PETITION FOR LETTERS OF ADMINISTRATION",
      "Rulings": "Continued to 04/05/2021. 1) The petition must be amended to identify the predeceased sibling and his surviving issue at item 8. Notice must be given to the omitted issue. The amendment or amended petition requires new notice including new publication. CRC 7.53(a). 2) The omitted issue must sign bond waivers.",
      "Judge": "Edward Miyauchi"
    },
    {
      "Case Number": "PES21304135",
      "Case Title": "THE ESTATE OF GLENN PATRICK VALUROSO",
      "Court Date": "2021-03-08 09:00 AM",
      "Examiner": "EDWARD MIYAUCHI",
      "Calendar Matter": "PETITION FOR LETTERS OF ADMINISTRATION",
      "Rulings": "Continued to 04/05/2021 to be heard with the related estate (PES-21-304134). A courtesy copy of the supplement must be received by 03/26/2021.",
      "Judge": "Edward Miyauchi"
    },
    {
      "Case Number": "PES21304170",
      "Case Title": "THE ESTATE OF JAMES M. DOAN",
      "Court Date": "2021-03-08 09:00 AM",
      "Examiner": "SANDRA HILTON",
      "Calendar Matter": "PETITION FOR LETTERS OF ADMINISTRATION",
      "Rulings": "grant without hearing. close of estate set for 9/6/22.",
      "Judge": "Sandra Hilton"
    },
    {
      "Case Number": "PES21304190",
      "Case Title": "THE ESTATE OF ROSANNE CAPALBO",
      "Court Date": "2021-03-08 09:00 AM",
      "Examiner": "HELEN TROWBRIDGE",
      "Calendar Matter": "PETITION FOR LETTERS OF ADMINISTRATION",
      "Rulings": "Continued to 3/24/21. No courtesy copies. No proposed order. No proof of service. No Duties & Liabilities (with Confidential Statement). [LRSF 2.7 B., 14.7 A. and B., and 14.18 E.] Courtesy copies and a proposed order must be received by the assigned Examiner by no later than 3/17/21.",
      "Judge": "Helen Trowbridge"
    },
    {
      "Case Number": "PES21304193",
      "Case Title": "THE ESTATE OF TIMOTHY A. CRAMER",
      "Court Date": "2021-03-08 09:00 AM",
      "Examiner": "EDWARD MIYAUCHI",
      "Calendar Matter": "PETITION FOR LETTERS OF ADMINISTRATION",
      "Rulings": "Grant without hearing, subject to $20,000 bond with consent of counsel. No conformed copy of signed order will be returned (no self-addressed stamped envelope provided). Petition for final distribution or petition for approval of report of status of administration must be filed by 08/22/2022. If not on file, appearance required at status hearing set for 09/06/2022.",
      "Judge": "Edward Miyauchi"
    },
    {
      "Case Number": "PES21304195",
      "Case Title": "THE ESTATE OF GARY E. LANZA",
      "Court Date": "2021-03-08 09:00 AM",
      "Examiner": "BRANDON SLYKHOUS",
      "Calendar Matter": "PETITION FOR LETTERS OF ADMINISTRATION",
      "Rulings": "Grant without hearing. status on close 9/7/2022.",
      "Judge": "Brandon Slykhous"
    }
  ],
  "_date": "2021-03-08"
}