{
  "department": "204",
  "scraped_at": "2026-05-03T07:31:04.322Z",
  "source_url": "https://webapps.sftc.org/tr/tr.dll?RulingID=7&SessionID=EBCD4C46A9962A4CD0D10311E44F3F7A91E222B6",
  "reported_total": 48,
  "rulings": [
    {
      "Case Number": "PGN10293156",
      "Case Title": "GUARDIANSHIP OF FELIX M. BUCKBERG MICHAEL et al",
      "Court Date": "2025-08-20 09:00 AM",
      "Examiner": "AERO FETH",
      "Calendar Matter": "ACCOUNTING PETITION RE: Report",
      "Rulings": "Hearing. Appearance required of the ward pursuant to LRSF 14.A.2. Please have the CASE NUMBER and the CASE NAME ready for the clerk. Parties appearing must check in for the hearing using their FULL NAME. Counsel and parties may appear in person or remotely through Zoom or CourtCall. Please review LRSF 14.1. For Zoom appearance: meeting ID is 160 225 4765 and password is 514879. For audio-only telephone appearance via Zoom, call 1-669-254-5252 and follow the prompts, using the meeting ID and password above. Counsel and parties may appear by audio-only telephone through CourtCall by calling 1-888-882-6878.",
      "Judge": "Aero Feth"
    },
    {
      "Case Number": "PGN17301232",
      "Case Title": "GUARDIANSHIP OF ROWAN STRUMMER TELLES",
      "Court Date": "2025-08-20 09:00 AM",
      "Examiner": "AERO FETH",
      "Calendar Matter": "ACCOUNTING PETITION RE: Accounting #4, Report, Fees",
      "Rulings": "Continued to 10/01/2025. Updated notes emailed to counsel on 08/15/2025.",
      "Judge": "Aero Feth"
    },
    {
      "Case Number": "PGN20303550",
      "Case Title": "GUARDIANSHIP OF COLETTE FISHER ET AL",
      "Court Date": "2025-08-20 09:00 AM",
      "Examiner": "AERO FETH",
      "Calendar Matter": "ANNUAL WRITTEN STATUS REPORT AND ANNUAL BANK STATEMENT DUE",
      "Rulings": "Off calendar",
      "Judge": "Aero Feth"
    },
    {
      "Case Number": "PES21304914",
      "Case Title": "THE ESTATE OF EUGENIO S. AMADOR",
      "Court Date": "2025-08-20 09:00 AM",
      "Examiner": "EDWARD MIYAUCHI",
      "Calendar Matter": "ACCOUNTING PETITION RE: Accounting #1, Report, Fees, Final Distribution",
      "Rulings": "Continued to 09/16/2025 (no earlier date available). Notes were e-mailed to counsel on 08/13/2025. Updated/additional notes were e-mailed to counsel on 08/15/2025 upon review of supplemental papers filed in response to initial notes.",
      "Judge": "Edward Miyauchi"
    },
    {
      "Case Number": "PCN21304950",
      "Case Title": "CONSERVATORSHIP OF MALEE TANG",
      "Court Date": "2025-08-20 09:00 AM",
      "Examiner": "EDWARD MIYAUCHI",
      "Calendar Matter": "ACCOUNTING PETITION RE: Accounting #1, Report",
      "Rulings": "Continued to 09/17/2025. 1) Notice of the third amended petition must be given to the conservatee on the mandatory Judicial Council form GC-020 with a copy of the remote appearance information required by LRSF 14.1(C)(6) attached. 2) The correct date must be stated on petitioner's verification attached to the third amended petition.",
      "Judge": "Edward Miyauchi"
    },
    {
      "Case Number": "PES21305028",
      "Case Title": "THE ESTATE OF JIAJUN TAN",
      "Court Date": "2025-08-20 09:00 AM",
      "Examiner": "SEAN BANG",
      "Calendar Matter": "REPORT OF STATUS OF ADMINISTRATION",
      "Rulings": "Continued to 9/17/25 for notice of hearing to be filed.",
      "Judge": "Sean Bang"
    },
    {
      "Case Number": "PES22305252",
      "Case Title": "THE ESTATE OF TONY ALAN HOLLIFIELD",
      "Court Date": "2025-08-20 09:00 AM",
      "Examiner": "SEAN BANG",
      "Calendar Matter": "ACCOUNTING PETITION RE: Final Distribution",
      "Rulings": "Continued to 9/23/25 for failure to address prior tentative ruling. All documents to be filed by 9/8/25.",
      "Judge": "Sean Bang"
    },
    {
      "Case Number": "PTR22305483",
      "Case Title": "IN THE MATTER OF THE TRUST CREATED UNDER THE LAST WILL & TESTAMENT OF ETTA BACHARACH",
      "Court Date": "2025-08-20 14:30 PM",
      "Examiner": "ELIF SONMEZ",
      "Calendar Matter": "Temporary Trustees Motion To Compel Compliance And For Order To Show Cause Why Respondent Mark Borsuk Should Not Be Held In Contempt",
      "Rulings": "Hearing will be continued to September 17, 2025 at 2:30 p.m., per court's availability.",
      "Judge": "Elif Sonmez"
    },
    {
      "Case Number": "PES22305500",
      "Case Title": "THE ESTATE OF RONALD DEAN COLEMAN",
      "Court Date": "2025-08-20 09:00 AM",
      "Examiner": "HELEN TROWBRIDGE",
      "Calendar Matter": "REPORT OF STATUS OF ADMINISTRATION",
      "Rulings": "Granted per written order Status of filing a petition for final distribution will be set for 2/3/26. No appearance will be required on that date if a petition is filed by 1/20/26.",
      "Judge": "Helen Trowbridge"
    },
    {
      "Case Number": "PES22305512",
      "Case Title": "THE ESTATE OF AMANDA ALICE CARLIN CULLINAN",
      "Court Date": "2025-08-20 09:00 AM",
      "Examiner": "EDWARD MIYAUCHI",
      "Calendar Matter": "ADDED TO CALENDAR FOR Status Of Filing Receipts For Deposit Into Blocked Account",
      "Rulings": "OFF CALENDAR",
      "Judge": "Edward Miyauchi"
    },
    {
      "Case Number": "PES22305742",
      "Case Title": "THE ESTATE OF HULA MAE MCCLENDON",
      "Court Date": "2025-08-20 09:00 AM",
      "Examiner": "EDWARD MIYAUCHI",
      "Calendar Matter": "ADDED TO CALENDAR FOR Status Hearing For Filing Of A Petition For Final Distribution Or A Petition For Approval Of Report On Status Of Administration",
      "Rulings": "Hearing. Appearance required. PARTIES APPEARING SHOULD CHECK IN FOR THE HEARING WITH THEIR FULL NAME. Counsel and parties may appear personally or remotely through Zoom or CourtCall. For a video appearance, go to zoom.us, click \"join a meeting\" and input meeting ID 160 225 4765 and password 514879. For an audio-only appearance through Zoom, call 1-669-254-5252 and key in meeting ID \"160 225 4765#\", then participant ID \"0#\", then password \"514879#\". (Toll rates may apply).) The Court prefers that counsel and parties appearing by video input their first and last name into the \"Your Name\" dialogue box. Counsel and parties may appear by audio-only telephone through CourtCall by calling 1-888-882-6878. Please review LRSF 14.1(C) for more information.",
      "Judge": "Edward Miyauchi"
    },
    {
      "Case Number": "PES22305742",
      "Case Title": "THE ESTATE OF HULA MAE MCCLENDON",
      "Court Date": "2025-08-20 09:00 AM",
      "Examiner": "EDWARD MIYAUCHI",
      "Calendar Matter": "ADDED TO CALENDAR FOR Status On Filing Of The Receipts For The Blocked Accounts",
      "Rulings": "Hearing. Appearance required. PARTIES APPEARING SHOULD CHECK IN FOR THE HEARING WITH THEIR FULL NAME. Counsel and parties may appear personally or remotely through Zoom or CourtCall. For a video appearance, go to zoom.us, click \"join a meeting\" and input meeting ID 160 225 4765 and password 514879. For an audio-only appearance through Zoom, call 1-669-254-5252 and key in meeting ID \"160 225 4765#\", then participant ID \"0#\", then password \"514879#\". (Toll rates may apply).) The Court prefers that counsel and parties appearing by video input their first and last name into the \"Your Name\" dialogue box. Counsel and parties may appear by audio-only telephone through CourtCall by calling 1-888-882-6878. Please review LRSF 14.1(C) for more information.",
      "Judge": "Edward Miyauchi"
    },
    {
      "Case Number": "PES22305742",
      "Case Title": "THE ESTATE OF HULA MAE MCCLENDON",
      "Court Date": "2025-08-20 09:00 AM",
      "Examiner": "EDWARD MIYAUCHI",
      "Calendar Matter": "ORDER OF STATUS HEARING",
      "Rulings": "Hearing. Appearance required. PARTIES APPEARING SHOULD CHECK IN FOR THE HEARING WITH THEIR FULL NAME. Counsel and parties may appear personally or remotely through Zoom or CourtCall. For a video appearance, go to zoom.us, click \"join a meeting\" and input meeting ID 160 225 4765 and password 514879. For an audio-only appearance through Zoom, call 1-669-254-5252 and key in meeting ID \"160 225 4765#\", then participant ID \"0#\", then password \"514879#\". (Toll rates may apply).) The Court prefers that counsel and parties appearing by video input their first and last name into the \"Your Name\" dialogue box. Counsel and parties may appear by audio-only telephone through CourtCall by calling 1-888-882-6878. Please review LRSF 14.1(C) for more information.",
      "Judge": "Edward Miyauchi"
    },
    {
      "Case Number": "PES22305858",
      "Case Title": "THE ESTATE OF FRANK SHIGERU MATSUNO",
      "Court Date": "2025-08-20 09:00 AM",
      "Examiner": "SEAN BANG",
      "Calendar Matter": "ACCOUNTING PETITION RE: Fees, Final Distribution",
      "Rulings": "Grant without hearing.",
      "Judge": "Sean Bang"
    },
    {
      "Case Number": "PES23305934",
      "Case Title": "THE ESTATE OF IDA MAE JONES",
      "Court Date": "2025-08-20 09:00 AM",
      "Examiner": "SEAN BANG",
      "Calendar Matter": "ACCOUNTING PETITION RE: Accounting #1, Report",
      "Rulings": "Continued to 9/23/25 for failure to address Examiner's Notes. All documents to be filed by 9/8/25.",
      "Judge": "Sean Bang"
    },
    {
      "Case Number": "PGN23306041",
      "Case Title": "GUARDIANSHIP OF ISAAC STRAUS HAYMAKER",
      "Court Date": "2025-08-20 09:00 AM",
      "Examiner": "HELEN TROWBRIDGE",
      "Calendar Matter": "ANNUAL WRITTEN STATUS REPORT AND ANNUAL BANK STATEMENT DUE",
      "Rulings": "OFF CALENDAR",
      "Judge": "Helen Trowbridge"
    },
    {
      "Case Number": "PCN23306261",
      "Case Title": "CONSERVATORSHIP OF ANNE B. MITCHELL",
      "Court Date": "2025-08-20 09:00 AM",
      "Examiner": "HELEN TROWBRIDGE",
      "Calendar Matter": "ACCOUNTING PETITION RE: Accounting #1, Report, Fees",
      "Rulings": "Grant without hearing. (The beginning balance of the Wells Fargo Checking account shown in the I&A appears, from the bank statement, to have been the correct amount as of 5/23/23.)",
      "Judge": "Helen Trowbridge"
    },
    {
      "Case Number": "PES23306274",
      "Case Title": "THE ESTATE OF DONALD RAY FUNKHOUSER",
      "Court Date": "2025-08-20 09:00 AM",
      "Examiner": "HELEN TROWBRIDGE",
      "Calendar Matter": "ACCOUNTING PETITION RE: Accounting #1, Report, Fees, Final Distribution",
      "Rulings": "Granted per written order The Court notes, however, that the same attorney represented both the assignors and the assignee but no waiver of the conflict appears to have been filed.",
      "Judge": "Helen Trowbridge"
    },
    {
      "Case Number": "PES23306340",
      "Case Title": "THE ESTATE OF MARIE CONROY",
      "Court Date": "2025-08-20 09:00 AM",
      "Examiner": "EDWARD MIYAUCHI",
      "Calendar Matter": "REPORT OF STATUS OF ADMINISTRATION",
      "Rulings": "Grant without hearing. Status hearing on filing of petition for final distribution or petition for approval on report of status of administration will be set for 06/16/2026.",
      "Judge": "Edward Miyauchi"
    },
    {
      "Case Number": "PCN23306642",
      "Case Title": "CONSERVATORSHIP OF PAUL SEGAL",
      "Court Date": "2025-08-20 09:00 AM",
      "Examiner": "EDWARD MIYAUCHI",
      "Calendar Matter": "ACCOUNTING PETITION RE: Accounting #1, Report, Fees",
      "Rulings": "Continued to 10/15/2025, as nothing has been filed to address the issues (e-mailed to counsel on 06/10/2025).",
      "Judge": "Edward Miyauchi"
    },
    {
      "Case Number": "PES23306648",
      "Case Title": "THE ESTATE OF WANDA MAY LOO",
      "Court Date": "2025-08-20 09:00 AM",
      "Examiner": "HELEN TROWBRIDGE",
      "Calendar Matter": "REPORT OF STATUS OF ADMINISTRATION",
      "Rulings": "OFF CALENDAR",
      "Judge": "Helen Trowbridge"
    },
    {
      "Case Number": "PTR23306674",
      "Case Title": "IN THE MATTER OF THE 2013 ANNE BOWIE MITCHELL REVOCABLE TRUST",
      "Court Date": "2025-08-20 09:00 AM",
      "Examiner": "HELEN TROWBRIDGE",
      "Calendar Matter": "ACCOUNTING PETITION RE: Accounting #1, Report, Fees",
      "Rulings": "Continued to 10/14/25. (No earlier availability.) 1. Please file a copy of the seller's closing statement. [Probate Code Section 20260(c)(3).] 2. Was the attorney cost for e-filing the I&A on 3/11/24 a duplicate of the one on 3/5/24? Courtesy copies of any new, responsive papers must be received by the assigned examiner by 9/30/25. Examiner continuances are final and not subject to contest under LRSF 14.10 B.",
      "Judge": "Helen Trowbridge"
    },
    {
      "Case Number": "PES23306732",
      "Case Title": "THE ESTATE OF WILLIAM JAMES ENGLAND",
      "Court Date": "2025-08-20 09:00 AM",
      "Examiner": "SEAN BANG",
      "Calendar Matter": "ACCOUNTING PETITION RE: Report, Fees, Final Distribution",
      "Rulings": "Continued to 10/7/25 at request of counsel.",
      "Judge": "Sean Bang"
    },
    {
      "Case Number": "PES23306760",
      "Case Title": "THE ESTATE OF DOUGLAS EARLE",
      "Court Date": "2025-08-20 09:00 AM",
      "Examiner": "SEAN BANG",
      "Calendar Matter": "ADDED TO CALENDAR FOR Status On Close Of Estate",
      "Rulings": "off calendar",
      "Judge": "Sean Bang"
    },
    {
      "Case Number": "PES23306834",
      "Case Title": "THE ESTATE OF VIOLET A. CORKERY",
      "Court Date": "2025-08-20 09:00 AM",
      "Examiner": "AERO FETH",
      "Calendar Matter": "ACCOUNTING PETITION RE: Report, Fees, Final Distribution",
      "Rulings": "Grant without hearing.",
      "Judge": "Aero Feth"
    },
    {
      "Case Number": "PES24306998",
      "Case Title": "THE ESTATE OF DELORISA TURNER",
      "Court Date": "2025-08-20 09:00 AM",
      "Examiner": "HELEN TROWBRIDGE",
      "Calendar Matter": "PETITION TO TERMINATE ESTATE (NO ASSETS)",
      "Rulings": "Continued to 10/15/25. (No earlier availability.) Issue(s) necessitating continuance: (1) No proposed order has been lodged or received by the assigned examiner. [LRSF 14.7 A. and 14.59 E.] (2) Notice must have attached to it the procedures for how to make a remote appearance by Zoom and CourtCall, as well as remote public access, as set out at https://sf.courts.ca.gov/divisions/probate-court. [LRSF 14.1 C.6.] (3) Notice was mailed to Shawn A. Turner at an address that is different from the address shown in the petition. (4) A proof of service, filed on 7/2/25, shows a different address for Javon C. White from the address shown in the petition, but a copy of the mandatory Judicial Council form DE-120 Notice of Hearing was not attached to that pleading form of proof of service and nothing has been filed to indicate that his address is different from the one set forth in the petition. Please provide a proposed order and courtesy copies of any papers filed to address these issues to the assigned examiner by 10/1/15. Examiner continuances are final and not subject to contest under LRSF 14.10 B. (The decedent was reported to have died on 10/1/20, not 10/10/20.)",
      "Judge": "Helen Trowbridge"
    },
    {
      "Case Number": "PTR24307006",
      "Case Title": "IN THE MATTER OF THE RICHARD P. GRANZELLA TRUST TRUST",
      "Court Date": "2025-08-20 09:00 AM",
      "Examiner": "EDWARD MIYAUCHI",
      "Calendar Matter": "ORDER OF STATUS HEARING",
      "Rulings": "Hearing. Appearance required. PARTIES APPEARING SHOULD CHECK IN FOR THE HEARING WITH THEIR FULL NAME. Counsel and parties may appear personally or remotely through Zoom or CourtCall. For a video appearance, go to zoom.us, click \"join a meeting\" and input meeting ID 160 225 4765 and password 514879. For an audio-only appearance through Zoom, call 1-669-254-5252 and key in meeting ID \"160 225 4765#\", then participant ID \"0#\", then password \"514879#\". (Toll rates may apply).) The Court prefers that counsel and parties appearing by video input their first and last name into the \"Your Name\" dialogue box. Counsel and parties may appear by audio-only telephone through CourtCall by calling 1-888-882-6878. Please review LRSF 14.1(C) for more information.",
      "Judge": "Edward Miyauchi"
    },
    {
      "Case Number": "PTR24307006",
      "Case Title": "IN THE MATTER OF THE RICHARD P. GRANZELLA TRUST TRUST",
      "Court Date": "2025-08-20 09:00 AM",
      "Examiner": "EDWARD MIYAUCHI",
      "Calendar Matter": "ADDED TO CALENDAR FOR Petition 1) For Remedy For Breach Of Trust By Trustee; 2) To Compel Accounting; 3) For Instructions To Sell Trust Real Property; 4) To Suspend And Remove Trustee; 5) For Appointment Of Professional Fiduciary Trustee; 6) For Denial Of Trustee Compensation; 7) For Surcharge; And 8) Attorneys' Fees",
      "Rulings": "Hearing. Appearance required. PARTIES APPEARING SHOULD CHECK IN FOR THE HEARING WITH THEIR FULL NAME. Counsel and parties may appear personally or remotely through Zoom or CourtCall. For a video appearance, go to zoom.us, click \"join a meeting\" and input meeting ID 160 225 4765 and password 514879. For an audio-only appearance through Zoom, call 1-669-254-5252 and key in meeting ID \"160 225 4765#\", then participant ID \"0#\", then password \"514879#\". (Toll rates may apply).) The Court prefers that counsel and parties appearing by video input their first and last name into the \"Your Name\" dialogue box. Counsel and parties may appear by audio-only telephone through CourtCall by calling 1-888-882-6878. Please review LRSF 14.1(C) for more information.",
      "Judge": "Edward Miyauchi"
    },
    {
      "Case Number": "PTR24307006",
      "Case Title": "IN THE MATTER OF THE RICHARD P. GRANZELLA TRUST TRUST",
      "Court Date": "2025-08-20 09:00 AM",
      "Examiner": "EDWARD MIYAUCHI",
      "Calendar Matter": "Petition To 1) Invalidate Amendment (Prob Code 6104 And 811); 2) Remove Trustee; 3) Return Trust Property Prob Code 850 And 859; 4) Attorneys Fees",
      "Rulings": "Hearing. Appearance required. PARTIES APPEARING SHOULD CHECK IN FOR THE HEARING WITH THEIR FULL NAME. Counsel and parties may appear personally or remotely through Zoom or CourtCall. For a video appearance, go to zoom.us, click \"join a meeting\" and input meeting ID 160 225 4765 and password 514879. For an audio-only appearance through Zoom, call 1-669-254-5252 and key in meeting ID \"160 225 4765#\", then participant ID \"0#\", then password \"514879#\". (Toll rates may apply).) The Court prefers that counsel and parties appearing by video input their first and last name into the \"Your Name\" dialogue box. Counsel and parties may appear by audio-only telephone through CourtCall by calling 1-888-882-6878. Please review LRSF 14.1(C) for more information.",
      "Judge": "Edward Miyauchi"
    },
    {
      "Case Number": "PTR24307099",
      "Case Title": "IN RE: THE AMENDED AND RESTATED MALEE TANG TRUST",
      "Court Date": "2025-08-20 09:00 AM",
      "Examiner": "HELEN TROWBRIDGE",
      "Calendar Matter": "ACCOUNTING PETITION RE: Accounting #1, Report",
      "Rulings": "Continued to 10/29/25 in light of the third amended account filed on 8/12/25 in the related conservtorship case. Also, issues posted in the tentative ruling for the hearing on 12/4/24 still have not been addressed. The proof of service filed on 8/6/25 did not have a copy of the instructions for how to appear remotely attached to the Notice of Hearing. [LRSF 14.1 C.6.]",
      "Judge": "Helen Trowbridge"
    },
    {
      "Case Number": "PES24307454",
      "Case Title": "THE ESTATE OF MICHAEL J. TEDESCHI",
      "Court Date": "2025-08-20 09:00 AM",
      "Examiner": "HELEN TROWBRIDGE",
      "Calendar Matter": "ACCOUNTING PETITION RE: Report, Fees, Final Distribution",
      "Rulings": "Continued to 10/15/25. (No earlier availability.) Issue(s) necessitating continuance: (1) The \"First Supplement\" filed on 7/2/25 AMENDED the petition. [See CRC 7.3.] (2) An amended pleading or an amendment to a pleading requires the same notice of hearing as the pleading it amends. [CRC 7.53(a).] (3) Madelane Dixon's current address was not set forth in any verified pleading. (4) The new Exhibit C attached to the \"First Supplement\" filed on 7/2/25 shows 954.78 shares of SIT New Beginning United St, but there were 9,554.78 shares inventoried and appraised at $107,969.01 (5) There were 63.48, not 61.4160, share of Invesco International Equit inventoried. (6) The 43.139 units of AB Global Bond Fund Inc Adv were appraised at $353.74, not $300.25. (7) There were 47.685, not 47.785, shares of American Century Internatio inventoried. (8) None of the holdings listed on the final page of Exhibit D to the \"First Supplement\" were on the I&A filed on 1/27/25. Please provide courtesy copies of any papers filed to address these issues to the assigned examiner by 10/1/25. Examiner continuances are final and not subject to contest under LRSF 14.10 B.",
      "Judge": "Helen Trowbridge"
    },
    {
      "Case Number": "PES24307526",
      "Case Title": "THE ESTATE OF WAI FOON MOY LEONG",
      "Court Date": "2025-08-20 09:00 AM",
      "Examiner": "AERO FETH",
      "Calendar Matter": "ACCOUNTING PETITION RE: Report, Fees, Final Distribution",
      "Rulings": "Grant without hearing.",
      "Judge": "Aero Feth"
    },
    {
      "Case Number": "PES24307532",
      "Case Title": "THE ESTATE OF LANCE ROBERT CALDER",
      "Court Date": "2025-08-20 09:00 AM",
      "Examiner": "EDWARD MIYAUCHI",
      "Calendar Matter": "ACCOUNTING PETITION RE: Accounting, Report, Fees, Final Distribution",
      "Rulings": "Grant without hearing.",
      "Judge": "Edward Miyauchi"
    },
    {
      "Case Number": "PES24307742",
      "Case Title": "THE ESTATE OF TINA MEI",
      "Court Date": "2025-08-20 09:00 AM",
      "Examiner": "AEYOUNG KIM",
      "Calendar Matter": "ACCOUNTING PETITION RE: Report, Fees, Final Distribution",
      "Rulings": "Continued to 10/14/25. The following issues to be cleared two weeks before: (1) Disclaimer is irrevocable and not an assignment, disposing of the disclaimed interests as if the disclaimant predeceased the decedent. Prob. Code sections. 281. Petitioner alleges that Ms. A. Mei has two children who are entitled to her share as a result of the disclaimer. It appears that the petition needs to be properly amended to mirror the said proposed distribution (to Ms. A. Mei's issues, considering one issue is a minor), or the petitioner needs to provide an authority under which the court can grant the proposed distribution of Ms. A. Mei's shares to the petitioner, not her children. (2) The date of birth of the minor child of Ms. A. Mei. (3) The children of the disclaimant must be properly noticed. (4) Assets included in the Inventory and Appraisal (I&A) must be identified to ensure that all accounts are accurately listed on Attachment 1. If any account contains securities held in a brokerage account, these must be appraised by the probate referee. Listing merely financial institutions' names are insufficient. In such cases, a new probate referee must be appointed, and a corrected Inventory and Appraisal must be submitted. Examiner continuances are final and not subject to contest under LRSF 14.10.B.",
      "Judge": "Aeyoung Kim"
    },
    {
      "Case Number": "PCN24307954",
      "Case Title": "CONSERVATORSHIP OF JOAN URDANG",
      "Court Date": "2025-08-20 09:00 AM",
      "Examiner": "SEAN BANG",
      "Calendar Matter": "ADDED TO CALENDAR FOR A Compliance Status Hearing Is Set For Compliance With The Following Additional Orders Of The Court:",
      "Rulings": "Continued to 9/17/25 for filing of notice of filing the final I&A.",
      "Judge": "Sean Bang"
    },
    {
      "Case Number": "PES24307978",
      "Case Title": "THE ESTATE OF FRANK S.Y. CHIN",
      "Court Date": "2025-08-20 09:00 AM",
      "Examiner": "EDWARD MIYAUCHI",
      "Calendar Matter": "PETITION FOR SPOUSAL PROPERTY",
      "Rulings": "Hearing. Appearance required. PARTIES APPEARING SHOULD CHECK IN FOR THE HEARING WITH THEIR FULL NAME. Counsel and parties may appear personally or remotely through Zoom or CourtCall. For a video appearance, go to zoom.us, click \"join a meeting\" and input meeting ID 160 225 4765 and password 514879. For an audio-only appearance through Zoom, call 1-669-254-5252 and key in meeting ID \"160 225 4765#\", then participant ID \"0#\", then password \"514879#\". (Toll rates may apply).) The Court prefers that counsel and parties appearing by video input their first and last name into the \"Your Name\" dialogue box. Counsel and parties may appear by audio-only telephone through CourtCall by calling 1-888-882-6878. Please review LRSF 14.1(C) for more information.",
      "Judge": "Edward Miyauchi"
    },
    {
      "Case Number": "PES24307991",
      "Case Title": "THE ESTATE OF GEORGE F THOMAS",
      "Court Date": "2025-08-20 14:00 PM",
      "Examiner": "ELIF SONMEZ",
      "Calendar Matter": "Notice Of Demurrer And Demurrer Of Petitioner Wells Fargo Bank, N.A. To Will Contest Of Bin Bin Thomas",
      "Rulings": "Hearing will be continued to September 17, 2025 at 2:00 p.m., due to availability of the court.",
      "Judge": "Elif Sonmez"
    },
    {
      "Case Number": "PCN24308041",
      "Case Title": "CONSERVATORSHIP OF WE YANG",
      "Court Date": "2025-08-20 09:00 AM",
      "Examiner": "AEYOUNG KIM",
      "Calendar Matter": "ADDED TO CALENDAR FOR A Compliance Status Hearing",
      "Rulings": "Off calendar.",
      "Judge": "Aeyoung Kim"
    },
    {
      "Case Number": "PTR25308070",
      "Case Title": "IN THE MATTER OF THE NABIHA SHATARA DABIT 2016 REVOCABLE TRUST",
      "Court Date": "2025-08-20 09:00 AM",
      "Examiner": "SEAN BANG",
      "Calendar Matter": "Petition For An Order: 1. Immediately Suspending & Removing Respondent As Trustee, 2. Appointing A Professional Fiducary As Successor Trustee; 3. Requiring Respondent To Redress The Trust & An Award Of Double Damages; 4. Compelling Respondent To Submit Two Separate Accountings; 5. Enjoining Respondent From Using Trust Funds To Defend Against The Petition; 6. For An Award Of Payment Of Petitioner'S Attorney Fees And Costs",
      "Rulings": "Continued to 8/25/25 to be heard by Judge Moody.",
      "Judge": "Sean Bang"
    },
    {
      "Case Number": "PES25308130",
      "Case Title": "THE ESTATE OF MICHAEL SPISAK",
      "Court Date": "2025-08-20 09:00 AM",
      "Examiner": "SEAN BANG",
      "Calendar Matter": "PETITION FOR LETTERS OF ADMINISTRATION",
      "Rulings": "Appearance required. Remote appearances may be made. Please review Local Rule 14.1. The following information pertains to appearances by Zoom: WHEN ENTERING \"YOUR NAME\" ON ZOOM, BOTH THE FIRST AND LAST NAME, AS WELL THE CASE NUMBER, MUST BE INCLUDED. Meeting ID: 160 225 4765 Password: 514879 To appear by telephone through Zoom, call 1-669-254-5252, and follow the prompts, using the meeting ID and password above.",
      "Judge": "Sean Bang"
    },
    {
      "Case Number": "PTR25308284",
      "Case Title": "IN THE MATTER OF THE THE FRANK S.Y. CHIN REVOCABLE TRUST TRUST",
      "Court Date": "2025-08-20 09:00 AM",
      "Examiner": "HELEN TROWBRIDGE",
      "Calendar Matter": "Petition For Order Confirming Trust Assets",
      "Rulings": "Hearing. Appearance required. Some of the issues to be addressed: 1) No legal authority is cited in the petition aside from the caption. No pour-over will has been submitted either. 2) The Grant Deed recorded on 4/27/01 granted a 1/2 interest to Frank S.Y. Chin and Jean Y. Chin, husband and wife, as tenants in common, not joint tenants, as alleged in paragraph 4 of the petition. 3) A copy of a supplement must be served if a copy of the pleading was required (as with Probate Code Section 850 petitions). [CRC 7.53(b).] 4) The case number is incomplete in the caption of the supplement filed on 6/16/25 and the notices of hearing filed on 6/16/25 and 7/17/25. 5) It appears that the decedent's interest in the real property was more than 25%. Please have the CASE NUMBER and the CASE NAME ready for the clerk. Parties appearing must check in for the hearing using their FULL NAME. Counsel and parties may appear in person or remotely through Zoom or CourtCall. Please review LRSF 14.1 D. for information on remote appearances. For Zoom appearance: meeting ID is 160 225 4765 and password is 514879. For audio-only telephone appearance via Zoom, call 1-669-254-5252 and follow the prompts, using the meeting ID and password above. Counsel and parties may appear by audio-only telephone through CourtCall by calling 1-888-882-6878.",
      "Judge": "Helen Trowbridge"
    },
    {
      "Case Number": "PES25308304",
      "Case Title": "THE ESTATE OF FREDERICK WILLIAM COMFORT JR",
      "Court Date": "2025-08-20 09:00 AM",
      "Examiner": "AERO FETH",
      "Calendar Matter": "PETITION FOR PROBATE OF WILL AND FOR LETTERS TESTAMENTARY",
      "Rulings": "Continued to 10/15/2025. No response to notes sent 05/02/2025.",
      "Judge": "Aero Feth"
    },
    {
      "Case Number": "PTR25308442",
      "Case Title": "IN THE MATTER OF THE YANG FAMILY REVOCABLE TRUST TRUST",
      "Court Date": "2025-08-20 09:00 AM",
      "Examiner": "EDWARD MIYAUCHI",
      "Calendar Matter": "Petition For Order Approving Instructions And For Modificatoin Of Trust",
      "Rulings": "Grant without hearing, subject to modification of relief and proposed order with consent of counsel (via e-mail on 07/23/2025).",
      "Judge": "Edward Miyauchi"
    },
    {
      "Case Number": "PES25308524",
      "Case Title": "THE ESTATE OF MARY A.L. CHUNG",
      "Court Date": "2025-08-20 09:00 AM",
      "Examiner": "HELEN TROWBRIDGE",
      "Calendar Matter": "PETITION FOR PROBATE OF WILL AND FOR LETTERS TESTAMENTARY",
      "Rulings": "Hearing for the sole purpose of admitting the will dated 6/6/16. [Probate Code Section 8225.] No appearance is required. Status hearing will be set for 3/2/27. If a petition for final distribution or a report of status with a petition requesting additional time for estate administration is filed at least two weeks before that status hearing date, no appearance will be required on that date. (The Court will waive the minor defects in the petition. Item 3g(1)(d) of the petition is supposed to be checked when other named executors will not act because of death or declination or some other reason. The first named executor, Burk H. Lim, is deceased. Also, the trust beneficiaries are not specifically identified as such in the \"Supplemental Declaration in Response to Probate Examiner's Comments\" filed on 7/23/25. NB: A supplement or an amendment to a petition should stand on its own and not \"respond\" to issues raised by the court.)",
      "Judge": "Helen Trowbridge"
    },
    {
      "Case Number": "PCN25308603",
      "Case Title": "CONSERVATORSHIP OF DOROTHY JEAN BERNSTEIN STUBBLEFIELD LEWIS",
      "Court Date": "2025-08-20 13:30 PM",
      "Examiner": "ELIF SONMEZ",
      "Calendar Matter": "ADDED TO CALENDAR FOR Notice Of Court Hearing Re: Temporary Restraining Order",
      "Rulings": "Hearing continued to September 3, 2025, at 1:30 p.m., at request of petitioning party.",
      "Judge": "Elif Sonmez"
    },
    {
      "Case Number": "PCN25308603",
      "Case Title": "CONSERVATORSHIP OF DOROTHY JEAN BERNSTEIN STUBBLEFIELD LEWIS",
      "Court Date": "2025-08-20 13:30 PM",
      "Examiner": "ELIF SONMEZ",
      "Calendar Matter": "ADDED TO CALENDAR FOR Notice Of Court Hearing Re: Temporary Restraining Order On Elder Abuse",
      "Rulings": "Hearing continued to September 3, 2025, at 1:30 p.m., at request of petitioning party.",
      "Judge": "Elif Sonmez"
    },
    {
      "Case Number": "PES25308638",
      "Case Title": "THE ESTATE OF LORNA GANLEY",
      "Court Date": "2025-08-20 09:00 AM",
      "Examiner": "AERO FETH",
      "Calendar Matter": "PETITION FOR LETTERS OF ADMINISTRATION WITH WILL ANNEXED",
      "Rulings": "Continued to 10/01/2025. Notes emailed to counsel on 08/15/2025.",
      "Judge": "Aero Feth"
    },
    {
      "Case Number": "PES25308640",
      "Case Title": "THE ESTATE OF JOHN DAVID LOPEZ",
      "Court Date": "2025-08-20 09:00 AM",
      "Examiner": "HELEN TROWBRIDGE",
      "Calendar Matter": "PETITION FOR LETTERS OF ADMINISTRATION",
      "Rulings": "Grant without hearing Status of closing the estate will be set for 3/9/2027. The administrator must file either a petition for final distribution or a petition for approval of report of status of administration pursuant to Prob. C. Section 12200 (requesting additional time for estate administration) at least two weeks before 3/9/2027. Appearance will be required on that status date if no petition has been filed.",
      "Judge": "Helen Trowbridge"
    }
  ],
  "_date": "2025-08-20"
}